[
  {
    "doctype": "article",
    "authors": [
      "Parc, L\u00e9na",
      "Bouchy, Fran\u00e7ois",
      "Cook, Neil J.",
      "Grieves, Nolan",
      "Artigau, \u00c9tienne",
      "L'Heureux, Alexandrine",
      "Doyon, Ren\u00e9",
      "Messias, Yuri S.",
      "Baron, Fr\u00e9d\u00e9rique",
      "Barros, Susana C. C.",
      "Benneke, Bj\u00f6rn",
      "Bonfils, Xavier",
      "Bryan, Marta",
      "Canto Martins, Bruno L.",
      "Cloutier, Ryan",
      "Cowan, Nicolas B.",
      "Brito de Freitas, Daniel",
      "De Medeiros, Jose Renan",
      "Delfosse, Xavier",
      "Delgado-Mena, Elisa",
      "Dumusque, Xavier",
      "Ehrenreich, David",
      "Figueira, Pedro",
      "Gonz\u00e1lez Hern\u00e1ndez, Jonay I.",
      "Lafreni\u00e8re, David",
      "de Castro Le\u00e3o, Izan",
      "Lovis, Christophe",
      "Malo, Lison",
      "Melo, Claudio",
      "Mignon, Lucile",
      "Mordasini, Christoph",
      "Pepe, Francesco",
      "Rebolo, Rafael",
      "Rowe, Jason",
      "Santos, Nuno C.",
      "S\u00e9gransan, Damien",
      "Su\u00e1rez Mascare\u00f1o, Alejandro",
      "Udry, St\u00e9phane",
      "Valencia, Diana",
      "Wade, Gregg",
      "Abreu, Manuel",
      "Aguiar, Jos\u00e9 L. A.",
      "Al Moulla, Khaled",
      "Allain, Guillaume",
      "Allart, Romain",
      "Almenara, Jose Manuel",
      "Arial, Tomy",
      "Auger, Hugues",
      "Bazinet, Luc",
      "Blind, Nicolas",
      "Bohlender, David",
      "Boisse, Isabelle",
      "Boucher, Anne",
      "Bourrier, Vincent",
      "Bovay, S\u00e9bastien",
      "Branco, Pedro",
      "Broeg, Christopher",
      "Brousseau, Denis",
      "Cabral, Alexandre",
      "Cadieux, Charles",
      "Carmona, Andres",
      "Carteret, Yann",
      "Challita, Zalpha",
      "Charbonneau, David",
      "Chazelas, Bruno",
      "Clark, Catherine A.",
      "Coelho, Jo\u00e3o",
      "Cointepas, Marion",
      "Collins, Karen A.",
      "Collins, Kevin I.",
      "Conod, Uriel",
      "Cristo, Eduardo",
      "Costa Silva, Ana Rita",
      "Darveau-Bernier, Antoine",
      "Dauplaise, Laurie",
      "Delisle, Jean-Baptiste",
      "de Lima Gomes, Roseane",
      "Faria, Jo\u00e3o",
      "Fontinele, Dasaev O.",
      "Forveille, Thierry",
      "Frensch, Yolanda G. C.",
      "Gagn\u00e9, Jonathan",
      "Genest, Fr\u00e9d\u00e9ric",
      "Genolet, Ludovic",
      "Gomes da Silva, Jo\u00e3o",
      "Gracia T\u00e9mich, F\u00e9lix",
      "Gromek, Nicole",
      "Hernandez, Olivier",
      "Hobson, Melissa J.",
      "Hoeijmakers, H. Jens",
      "Hubin, Norbert",
      "Jafariyazani, Marziye",
      "Jahandar, Farbod",
      "Jayawardhana, Ray",
      "K\u00e4ufl, Hans-Ulrich",
      "Kerley, Dan",
      "Kolb, Johann",
      "Krishnamurthy, Vigneshwaran",
      "Kung, Benjamin",
      "Lamontagne, Pierrot",
      "Larue, Pierre",
      "Leath, Henry",
      "Lim, Olivia",
      "Lo Curto, Gaspare",
      "Martins, Allan M.",
      "Matthews, Elisabeth C.",
      "Matthews, Jaymie",
      "Mayer, Jean-S\u00e9bastien",
      "Metchev, Stan",
      "Messamah, Lina",
      "Moranta, Leslie",
      "Mounzer, Dany",
      "Nari, Nicola",
      "Nielsen, Louise D.",
      "Osborn, Ares",
      "Ouellet, Mathieu",
      "Otegi, Jon",
      "Pasquini, Luca",
      "Passegger, Vera M.",
      "Pelletier, Stefan",
      "Peroux, C\u00e9line",
      "Piaulet-Ghorayeb, Caroline",
      "Plotnykov, Mykhaylo",
      "Pompei, Emanuela",
      "Poulin-Girard, Anne-Sophie",
      "Rasilla, Jos\u00e9 Luis",
      "Reshetov, Vladimir",
      "Saint-Antoine, Jonathan",
      "Sarajlic, Mirsad",
      "Saviane, Ivo",
      "Schnell, Robin",
      "Segovia, Alex",
      "Seidel, Julia",
      "Silber, Armin",
      "Sinclair, Peter",
      "Sordet, Michael",
      "Sosnowska, Danuta",
      "Srivastava, Avidaan",
      "Stefanov, Atanas K.",
      "Teixeira, M\u00e1rcio A.",
      "Thibault, Simon",
      "Vall\u00e9e, Philippe",
      "Vandal, Thomas",
      "Vaulato, Valentina",
      "Wardenier, Joost P.",
      "Wehbe, Bachar",
      "Weisserman, Drew",
      "Wevers, Ivan",
      "Wildi, Fran\u00e7ois",
      "Yariv, Vincent",
      "Zins, G\u00e9rard"
    ],
    "year": "2025",
    "pubdate": "2025-10-00",
    "doi": [
      "10.1051/0004-6361/202555684",
      "10.48550/arXiv.2510.14927"
    ],
    "title": "NIRPS and TESS reveal a peculiar system around the M dwarf TOI-756: A transiting sub-Neptune and a cold eccentric giant",
    "pub": "Astronomy and Astrophysics",
    "volume": "702",
    "page": "A138",
    "citations": 0,
    "url": "https://ui.adsabs.harvard.edu/abs/2025A&A...702A.138P"
  },
  {
    "doctype": "article",
    "authors": [
      "Bazinet, Luc",
      "Allart, Romain",
      "Benneke, Bj\u00f6rn",
      "Pelletier, Stefan",
      "Wardenier, Joost P.",
      "Cook, Neil J.",
      "Forveille, Thierry",
      "Nielsen, Louise D.",
      "Al Moulla, Khaled",
      "Artigau, \u00c9tienne",
      "Baron, Fr\u00e9d\u00e9rique",
      "Barros, Susana C. C.",
      "Bonfils, Xavier",
      "Bouchy, Fran\u00e7ois",
      "Bryan, Marta",
      "Canto Martins, Bruno L.",
      "Cloutier, Ryan",
      "Cowan, Nicolas B.",
      "Brito de Freitas, Daniel",
      "De Medeiros, Jose Renan",
      "Delfosse, Xavier",
      "Doyon, Ren\u00e9",
      "Dumusque, Xavier",
      "Ehrenreich, David",
      "Gonz\u00e1lez Hern\u00e1ndez, Jonay I.",
      "Lafreni\u00e8re, David",
      "de Castro Le\u00e3o, Izan",
      "Lovis, Christophe",
      "Malo, Lison",
      "Melo, Claudio",
      "Mignon, Lucile",
      "Mordasini, Christoph",
      "Pepe, Francesco",
      "Rebolo, Rafael",
      "Rowe, Jason",
      "Santos, Nuno C.",
      "S\u00e9gransan, Damien",
      "Su\u00e1rez Mascare\u00f1o, Alejandro",
      "Udry, St\u00e9phane",
      "Valencia, Diana",
      "Wade, Gregg",
      "Abreu, Manuel",
      "Aguiar, Jos\u00e9 L. A.",
      "Allain, Guillaume",
      "Arial, Tomy",
      "Auger, Hugues",
      "Blind, Nicolas",
      "Bohlender, David",
      "Boucher, Anne",
      "Bourrier, Vincent",
      "Bovay, S\u00e9bastien",
      "Broeg, Christopher",
      "Brousseau, Denis",
      "Cabral, Alexandre",
      "Cadieux, Charles",
      "Carmona, Andres",
      "Challita, Zalpha",
      "Chazelas, Bruno",
      "Coelho, Jo\u00e3o",
      "Cointepas, Marion",
      "Costa Silva, Ana Rita",
      "Coulombe, Louis-Philippe",
      "Cristo, Eduardo",
      "Darveau-Bernier, Antoine",
      "Dauplaise, Laurie",
      "de Lima Gomes, Roseane",
      "Fontinele, Dasaev O.",
      "Frensch, Yolanda G. C.",
      "Genest, Fr\u00e9d\u00e9ric",
      "Genolet, Ludovic",
      "Gracia T\u00e9mich, F\u00e9lix",
      "Hernandez, Olivier",
      "Hoeijmakers, H. Jens",
      "Hubin, Norbert",
      "Jayawardhana, Ray",
      "K\u00e4ufl, Hans-Ulrich",
      "Kerley, Dan",
      "Kolb, Johann",
      "Krishnamurthy, Vigneshwaran",
      "Kung, Benjamin",
      "Lamontagne, Pierrot",
      "Lim, Olivia",
      "Lo Curto, Gaspare",
      "Luis Rasilla, Jos\u00e9",
      "Martins, Allan M.",
      "Matthews, Jaymie",
      "Mayer, Jean-S\u00e9bastien",
      "Messias, Yuri S.",
      "Metchev, Stan",
      "Mounzer, Dany",
      "Nari, Nicola",
      "Osborn, Ares",
      "Ouellet, Mathieu",
      "Parc, L\u00e9na",
      "Pasquini, Luca",
      "Peroux, C\u00e9line",
      "Piaulet-Ghorayeb, Caroline",
      "Pompei, Emanuela",
      "Poulin-Girard, Anne-Sophie",
      "Reshetov, Vladimir",
      "Saint-Antoine, Jonathan",
      "Sarajlic, Mirsad",
      "Schnell, Robin",
      "Segovia, Alex",
      "Seidel, Julia",
      "Silber, Armin",
      "Sinclair, Peter",
      "Sordet, Michael",
      "Sosnowska, Danuta",
      "Srivastava, Avidaan",
      "Stefanov, Atanas K.",
      "Teixeira, M\u00e1rcio A.",
      "Thibault, Simon",
      "Vall\u00e9e, Philippe",
      "Vandal, Thomas",
      "Vaulato, Valentina",
      "Wehbe, Bachar",
      "Weisserman, Drew",
      "Wevers, Ivan",
      "Wildi, Fran\u00e7ois",
      "Yariv, Vincent",
      "Zins, G\u00e9rard"
    ],
    "year": "2025",
    "pubdate": "2025-09-00",
    "doi": [
      "10.1051/0004-6361/202553724",
      "10.48550/arXiv.2508.06626"
    ],
    "title": "Quantifying thermal water dissociation in the dayside photosphere of WASP-121 b using NIRPS",
    "pub": "Astronomy and Astrophysics",
    "volume": "701",
    "page": "A276",
    "citations": 3,
    "url": "https://ui.adsabs.harvard.edu/abs/2025A&A...701A.276B"
  },
  {
    "doctype": "article",
    "authors": [
      "Gomes da Silva, Jo\u00e3o",
      "Delgado-Mena, Elisa",
      "Santos, Nuno C.",
      "Monteiro, Telmo",
      "Larue, Pierre",
      "Su\u00e1rez Mascare\u00f1o, Alejandro",
      "Delfosse, Xavier",
      "Mignon, Lucile",
      "Artigau, \u00c9tienne",
      "Nari, Nicola",
      "Abreu, Manuel",
      "Aguiar, Jos\u00e9 L. A.",
      "Al Moulla, Khaled",
      "Allain, Guillaume",
      "Allart, Romain",
      "Arial, Tomy",
      "Auger, Hugues",
      "Baron, Fr\u00e9d\u00e9rique",
      "Barros, Susana C. C.",
      "Bazinet, Luc",
      "Benneke, Bj\u00f6rn",
      "Blind, Nicolas",
      "Bohlender, David",
      "Boisse, Isabelle",
      "Bonfils, Xavier",
      "Boucher, Anne",
      "Bouchy, Fran\u00e7ois",
      "Bourrier, Vincent",
      "Bovay, S\u00e9bastien",
      "Branco, Pedro",
      "Broeg, Christopher",
      "Brousseau, Denis",
      "Bruniquel, Vincent",
      "Bryan, Marta",
      "Cabral, Alexandre",
      "Cadieux, Charles",
      "Canto Martins, Bruno L.",
      "Carmona, Andres",
      "Carteret, Yann",
      "Challita, Zalpha",
      "Chazelas, Bruno",
      "Cloutier, Ryan",
      "Coelho, Jo\u00e3o",
      "Cointepas, Marion",
      "Conod, Uriel",
      "Cook, Neil J.",
      "Costa Silva, Ana Rita",
      "Cowan, Nicolas B.",
      "Cristo, Eduardo",
      "Darveau-Bernier, Antoine",
      "Dauplaise, Laurie",
      "de Lima Gomes, Roseane",
      "De Medeiros, Jose Renan",
      "Delisle, Jean-Baptiste",
      "Doshi, Dhvani",
      "Doyon, Ren\u00e9",
      "Dumusque, Xavier",
      "Ehrenreich, David",
      "Figueira, Pedro",
      "Fontinele, Dasaev O.",
      "Forveille, Thierry",
      "Frensch, Yolanda G. C.",
      "Gagn\u00e9, Jonathan",
      "Genest, Fr\u00e9d\u00e9ric",
      "Genolet, Ludovic",
      "Gonz\u00e1lez Hern\u00e1ndez, Jonay I.",
      "Glover, Jennifer",
      "Gracia T\u00e9mich, F\u00e9lix",
      "Grieves, Nolan",
      "Gromek, Nicole",
      "Hernandez, Olivier",
      "Hobson, Melissa J.",
      "Hoeijmakers, H. Jens",
      "Hubin, Norbert",
      "Jahandar, Farbod",
      "Jayawardhana, Ray",
      "K\u00e4ufl, Hans-Ulrich",
      "Kerley, Dan",
      "Kolb, Johann",
      "Krishnamurthy, Vigneshwaran",
      "Kung, Benjamin",
      "L'Heureux, Alexandrine",
      "Lafreni\u00e8re, David",
      "Lamontagne, Pierrot",
      "de Castro Le\u00e3o, Izan",
      "Leath, Henry",
      "Lim, Olivia",
      "Lipper, Justin",
      "Lo Curto, Gaspare",
      "Lovis, Christophe",
      "Malo, Lison",
      "Martins, Allan M.",
      "Matthews, Jaymie",
      "Mayer, Jean-S\u00e9bastien",
      "Melo, Claudio",
      "Messamah, Lina",
      "Messias, Yuri S.",
      "Metchev, Stan",
      "Moranta, Leslie",
      "Mordasini, Christoph",
      "Mounzer, Dany",
      "Mraz, Georgia",
      "Nielsen, Louise D.",
      "Osborn, Ares",
      "Otegi, Jon",
      "Ouellet, Mathieu",
      "Parc, L\u00e9na",
      "Pasquini, Luca",
      "Passegger, Vera M.",
      "Pelletier, Stefan",
      "Pepe, Francesco",
      "Peroux, C\u00e9line",
      "Piaulet-Ghorayeb, Caroline",
      "Plotnykov, Mykhaylo",
      "Pompei, Emanuela",
      "Poulin-Girard, Anne-Sophie",
      "Rasilla, Jos\u00e9 Luis",
      "Rebolo, Rafael",
      "Reshetov, Vladimir",
      "Rowe, Jason",
      "Saint-Antoine, Jonathan",
      "Sarajlic, Mirsad",
      "Saviane, Ivo",
      "Schnell, Robin",
      "Segovia, Alex",
      "S\u00e9gransan, Damien",
      "Seidel, Julia",
      "Silber, Armin",
      "Sinclair, Peter",
      "Sordet, Michael",
      "Sosnowska, Danuta",
      "Srivastava, Avidaan",
      "Stefanov, Atanas K.",
      "Teixeira, M\u00e1rcio A.",
      "Thibault, Simon",
      "Udry, St\u00e9phane",
      "Valencia, Diana",
      "Vall\u00e9e, Philippe",
      "Vandal, Thomas",
      "Vaulato, Valentina",
      "Wade, Gregg",
      "Wardenier, Joost P.",
      "Wehbe, Bachar",
      "Weisserman, Drew",
      "Wevers, Ivan",
      "Wildi, Fran\u00e7ois",
      "Yariv, Vincent",
      "Zins, G\u00e9rard"
    ],
    "year": "2025",
    "pubdate": "2025-08-00",
    "doi": [
      "10.1051/0004-6361/202555013",
      "10.48550/arXiv.2507.21262"
    ],
    "title": "Blind search for activity-sensitive lines in the near-infrared using HARPS and NIRPS observations of Proxima and Gl 581",
    "pub": "Astronomy and Astrophysics",
    "volume": "700",
    "page": "A177",
    "citations": 1,
    "url": "https://ui.adsabs.harvard.edu/abs/2025A&A...700A.177G"
  },
  {
    "doctype": "article",
    "authors": [
      "Vaulato, Valentina",
      "Pelletier, Stefan",
      "Ehrenreich, David",
      "Allart, Romain",
      "Cristo, Eduardo",
      "Steiner, Michal",
      "Dumusque, Xavier",
      "Chakraborty, Hritam",
      "Lendl, Monika",
      "Srivastava, Avidaan",
      "Artigau, \u00c9tienne",
      "Baron, Fr\u00e9d\u00e9rique",
      "Barros, Susana C. C.",
      "Benneke, Bj\u00f6rn",
      "Bonfils, Xavier",
      "Bouchy, Fran\u00e7ois",
      "Bryan, Marta",
      "Martins, Bruno L. Canto",
      "Cloutier, Ryan",
      "Cook, Neil J.",
      "Cowan, Nicolas B.",
      "De Medeiros, Jose Renan",
      "Delfosse, Xavier",
      "Doyon, Ren\u00e9",
      "Gonz\u00e1lez Hern\u00e1ndez, Jonay I.",
      "Lafreni\u00e8re, David",
      "de Castro Le\u00e3o, Izan",
      "Lovis, Christophe",
      "Malo, Lison",
      "Melo, Claudio",
      "Mignon, Lucile",
      "Mordasini, Christoph",
      "Pepe, Francesco",
      "Rebolo, Rafael",
      "Rowe, Jason",
      "Santos, Nuno C.",
      "S\u00e9gransan, Damien",
      "Su\u00e1rez Mascare\u00f1o, Alejandro",
      "Udry, St\u00e9phane",
      "Valencia, Diana",
      "Wade, Gregg",
      "Al Moulla, Khaled",
      "Almenara, Jose Manuel",
      "Akinsanmi, Babatunde",
      "Bazinet, Luc",
      "Bourrier, Vincent",
      "Cadieux, Charles",
      "Carmona, Andres",
      "Carteret, Yann",
      "Silva, Ana Rita Costa",
      "Darveau-Bernier, Antoine",
      "Dauplaise, Laurie",
      "de Lima Gomes, Roseane",
      "Delisle, Jean-Baptiste",
      "Forveille, Thierry",
      "Frensch, Yolanda",
      "Gagn\u00e9, Jonathan",
      "Genest, Fr\u00e9d\u00e9ric",
      "da Silva, Jo\u00e3o Gomes",
      "Grieves, Nolan",
      "Hobson, Melissa J.",
      "Krishnamurthy, Vigneshwaran",
      "L'Heureux, Alexandrine",
      "Lamontagne, Pierrot",
      "Larue, Pierre",
      "Lim, Olivia",
      "Lo Curto, Gaspare",
      "Messias, Yuri S.",
      "Moranta, Leslie",
      "Mounzer, Dany",
      "Nari, Nicola",
      "Osborn, Ares",
      "Parc, L\u00e9na",
      "Piaulet, Caroline",
      "Plotnykov, Mykhaylo",
      "Psaridi, Angelica",
      "Stefanov, Atanas K.",
      "Teixeira, M\u00e1rcio A.",
      "Vandal, Thomas",
      "Wardenier, Joost P.",
      "Weisserman, Drew",
      "Yariv, Vincent"
    ],
    "year": "2025",
    "pubdate": "2025-08-00",
    "doi": [
      "10.1051/0004-6361/202452972",
      "10.48550/arXiv.2507.21229"
    ],
    "title": "Hydride ion continuum hides absorption signatures in the NIRPS near-infrared transmission spectrum of the ultra-hot gas giant WASP-189b",
    "pub": "Astronomy and Astrophysics",
    "volume": "700",
    "page": "A9",
    "citations": 5,
    "url": "https://ui.adsabs.harvard.edu/abs/2025A&A...700A...9V"
  },
  {
    "doctype": "article",
    "authors": [
      "Bouchy, Fran\u00e7ois",
      "Doyon, Ren\u00e9",
      "Pepe, Francesco",
      "Melo, Claudio",
      "Artigau, \u00c9tienne",
      "Malo, Lison",
      "Wildi, Fran\u00e7ois",
      "Baron, Fr\u00e9d\u00e9rique",
      "Delfosse, Xavier",
      "De Medeiros, Jose Renan",
      "Rebolo, Rafael",
      "Santos, Nuno C.",
      "Wade, Gregg",
      "Allart, Romain",
      "Al Moulla, Khaled",
      "Blind, Nicolas",
      "Cadieux, Charles",
      "Canto Martins, Bruno L.",
      "Cook, Neil J.",
      "Dumusque, Xavier",
      "Frensch, Yolanda",
      "Genest, Fr\u00e9d\u00e9ric",
      "Gonz\u00e1lez Hern\u00e1ndez, Jonay I.",
      "Grieves, Nolan",
      "Lo Curto, Gaspare",
      "Lovis, Christophe",
      "Mignon, Lucile",
      "Nielsen, Louise D.",
      "Poulin-Girard, Anne-Sophie",
      "Rasilla, Jos\u00e9 Luis",
      "Reshetov, Vladimir",
      "Sosnowska, Danuta",
      "Sordet, Michael",
      "Saint-Antoine, Jonathan",
      "Su\u00e1rez Mascare\u00f1o, Alejandro",
      "Thibault, Simon",
      "Vall\u00e9e, Philippe",
      "Vandal, Thomas",
      "Abreu, Manuel",
      "Aguiar, Jos\u00e9 L. A.",
      "Allain, Guillaume",
      "Arial, Tomy",
      "Auger, Hugues",
      "Barros, Susana C. C.",
      "Bazinet, Luc",
      "Benneke, Bj\u00f6rn",
      "Bonfils, Xavier",
      "Boucher, Anne",
      "Bourrier, Vincent",
      "Bovay, S\u00e9bastien",
      "Broeg, Christopher",
      "Brousseau, Denis",
      "Bruniquel, Vincent",
      "Bryan, Marta",
      "Cabral, Alexandre",
      "Carmona, Andres",
      "Carteret, Yann",
      "Challita, Zalpha",
      "Chazelas, Bruno",
      "Cloutier, Ryan",
      "Coelho, Jo\u00e3o",
      "Cointepas, Marion",
      "Conod, Uriel",
      "Cowan, Nicolas B.",
      "Cristo, Eduardo",
      "Gomes da Silva, Jo\u00e3o",
      "Dauplaise, Laurie",
      "Darveau-Bernier, Antoine",
      "de Lima Gomes, Roseane",
      "de Freitas, Daniel Brito",
      "Delgado-Mena, Elisa",
      "Delisle, Jean-Baptiste",
      "Ehrenreich, David",
      "Faria, Jo\u00e3o",
      "Figueira, Pedro",
      "Fontinele, Dasaev O.",
      "Forveille, Thierry",
      "Gagn\u00e9, Jonathan",
      "Genolet, Ludovic",
      "T\u00e9mich, F\u00e9lix Gracia",
      "Hernandez, Olivier",
      "Hobson, Melissa J.",
      "Hoeijmakers, Jens",
      "Hubin, Norbert",
      "Jahandar, Farbod",
      "Jayawardhana, Ray",
      "K\u00e4ufl, Hans-Ulrich",
      "Kerley, Dan",
      "Kolb, Johann",
      "Krishnamurthy, Vigneshwaran",
      "Lafreni\u00e8re, David",
      "Lamontagne, Pierrot",
      "Larue, Pierre",
      "Leath, Henry",
      "L'Heureux, Alexandrine",
      "de Castro Le\u00e3o, Izan",
      "Lim, Olivia",
      "Martins, Allan M.",
      "Matthews, Jaymie",
      "Mayer, Jean-S\u00e9bastien",
      "Messias, Yuri S.",
      "Metchev, Stan",
      "Moranta, Leslie",
      "Mordasini, Christoph",
      "Mounzer, Dany",
      "Nari, Nicola",
      "Osborn, Ares",
      "Ouellet, Mathieu",
      "Otegi, Jon",
      "Parc, L\u00e9na",
      "Pasquini, Luca",
      "Passegger, Vera M.",
      "Pelletier, Stefan",
      "Peroux, C\u00e9line",
      "Piaulet-Ghorayeb, Caroline",
      "Plotnykov, Mykhaylo",
      "Pompei, Emanuela",
      "Rowe, Jason",
      "Sarajlic, Mirsad",
      "Segovia, Alex",
      "Seidel, Julia",
      "S\u00e9gransan, Damien",
      "Schnell, Robin",
      "Costa Silva, Ana Rita",
      "Srivastava, Avidaan",
      "Stefanov, Atanas K.",
      "Teixeira, M\u00e1rcio A.",
      "Udry, St\u00e9phane",
      "Valencia, Diana",
      "Vaulato, Valentina",
      "Wardenier, Joost P.",
      "Wehbe, Bachar",
      "Weisserman, Drew",
      "Wevers, Ivan",
      "Yariv, Vincent",
      "Zins, G\u00e9rard"
    ],
    "year": "2025",
    "pubdate": "2025-08-00",
    "doi": [
      "10.1051/0004-6361/202453341",
      "10.48550/arXiv.2507.21767"
    ],
    "title": "NIRPS joining HARPS at ESO 3.6 m: On-sky performance and science objectives",
    "pub": "Astronomy and Astrophysics",
    "volume": "700",
    "page": "A10",
    "citations": 14,
    "url": "https://ui.adsabs.harvard.edu/abs/2025A&A...700A..10B"
  },
  {
    "doctype": "article",
    "authors": [
      "Allart, Romain",
      "Carteret, Yann",
      "Bourrier, Vincent",
      "Mignon, Lucile",
      "Baron, Fr\u00e9d\u00e9rique",
      "Cadieux, Charles",
      "Carmona, Andres",
      "Lovis, Christophe",
      "Chakraborty, Hritam",
      "Delgado-Mena, Elisa",
      "Artigau, \u00c9tienne",
      "Barros, Susana C. C.",
      "Benneke, Bj\u00f6rn",
      "Bonfils, Xavier",
      "Bouchy, Fran\u00e7ois",
      "Bryan, Marta",
      "Canto Martins, Bruno L.",
      "Cloutier, Ryan",
      "Cook, Neil J.",
      "Cowan, Nicolas B.",
      "Delfosse, Xavier",
      "Doyon, Ren\u00e9",
      "Dumusque, Xavier",
      "Ehrenreich, David",
      "Gonz\u00e1lez Hern\u00e1ndez, Jonay I.",
      "Lafreni\u00e8re, David",
      "de Castro Le\u00e3o, Izan",
      "Malo, Lison",
      "Melo, Claudio",
      "Mordasini, Christoph",
      "Pepe, Francesco",
      "Rebolo, Rafael",
      "De Medeiros, Jose Renan",
      "Rowe, Jason",
      "Santos, Nuno C.",
      "S\u00e9gransan, Damien",
      "Su\u00e1rez Mascare\u00f1o, Alejandro",
      "Udry, St\u00e9phane",
      "Valencia, Diana",
      "Wade, Gregg",
      "Abreu, Manuel",
      "Aguiar, Jos\u00e9 L. A.",
      "Akinsanmi, Babatunde",
      "Allain, Guillaume",
      "Almenara, Jose Manuel",
      "Al Moulla, Khaled",
      "Arial, Tomy",
      "Auger, Hugues",
      "Bazinet, Luc",
      "Blind, Nicolas",
      "Boucher, Anne",
      "Broeg, Christopher",
      "Brousseau, Denis",
      "Cabral, Alexandre",
      "Challita, Zalpha",
      "Coelho, Jo\u00e3o",
      "Cointepas, Marion",
      "Silva, Ana Rita Costa",
      "Cristo, Eduardo",
      "Darveau-Bernier, Antoine",
      "Dauplaise, Laurie",
      "de Lima Gomes, Roseane",
      "de Freitas, Daniel Brito",
      "Fontinele, Dasaev O.",
      "Forveille, Thierry",
      "Frensch, Yolanda",
      "Gagn\u00e9, Jonathan",
      "Genest, Fr\u00e9d\u00e9ric",
      "Gracia T\u00e9mich, F\u00e9lix",
      "Grieves, Nolan",
      "Hernandez, Olivier",
      "Hoeijmakers, Jens",
      "Hubin, Norbert",
      "Jahandar, Farbod",
      "Jayawardhana, Ray",
      "Kerley, Dan",
      "Kolb, Johann",
      "Krishnamurthy, Vigneshwaran",
      "L'Heureux, Alexandrine",
      "Lendl, Monika",
      "Lim, Olivia",
      "Curto, Gaspare Lo",
      "Matthews, Jaymie",
      "Martins, Allan M.",
      "Mayer, Jean-S\u00e9bastien",
      "Metchev, Stan",
      "Messias, Yuri S.",
      "Moranta, Leslie",
      "Mounzer, Dany",
      "Nari, Nicola",
      "Nielsen, Louise D.",
      "Osborn, Ares",
      "Parc, L\u00e9na",
      "Pasquini, Luca",
      "Pelletier, Stefan",
      "Peroux, C\u00e9line",
      "Piaulet, Caroline",
      "Plotnykov, Mykhaylo",
      "Pompei, Emanuela",
      "Poulin-Girard, Anne-Sophie",
      "Psaridi, Angelica",
      "Rasilla, Jos\u00e9 Luis",
      "Reshetov, Vladimir",
      "Saint-Antoine, Jonathan",
      "Sanz-Forcada, Jorge",
      "Seidel, Julia",
      "Saviane, Ivo",
      "Gomes da Silva, Jo\u00e3o",
      "Sosnowska, Danuta",
      "Srivastava, Avidaan",
      "Stefanov, Atanas K.",
      "Teixeira, M\u00e1rcio A.",
      "Thibault, Simon",
      "Vall\u00e9e, Philippe",
      "Vandal, Thomas",
      "Vaulato, Valentina",
      "Wardenier, Joost P.",
      "Wehbe, Bachar",
      "Weisserman, Drew",
      "Wildi, Fran\u00e7ois",
      "Yariv, Vincent",
      "Zins, G\u00e9rard"
    ],
    "year": "2025",
    "pubdate": "2025-08-00",
    "doi": [
      "10.1051/0004-6361/202452525",
      "10.48550/arXiv.2507.21284"
    ],
    "title": "NIRPS detection of delayed atmospheric escape from the warm and misaligned Saturn-mass exoplanet WASP-69 b",
    "pub": "Astronomy and Astrophysics",
    "volume": "700",
    "page": "A7",
    "citations": 5,
    "url": "https://ui.adsabs.harvard.edu/abs/2025A&A...700A...7A"
  },
  {
    "doctype": "article",
    "authors": [
      "Su\u00e1rez Mascare\u00f1o, Alejandro",
      "Artigau, \u00c9tienne",
      "Mignon, Lucile",
      "Delfosse, Xavier",
      "Cook, Neil J.",
      "Bouchy, Fran\u00e7ois",
      "Doyon, Ren\u00e9",
      "Gonz\u00e1lez Hern\u00e1ndez, Jonay I.",
      "Vandal, Thomas",
      "de Castro Le\u00e3o, Izan",
      "Stefanov, Atanas K.",
      "Faria, Jo\u00e3o",
      "Cadieux, Charles",
      "Lamontagne, Pierrot",
      "Baron, Fr\u00e9d\u00e9rique",
      "Barros, Susana C. C.",
      "Benneke, Bj\u00f6rn",
      "Bonfils, Xavier",
      "Bryan, Marta",
      "Canto Martins, Bruno L.",
      "Cloutier, Ryan",
      "Cowan, Nicolas B.",
      "de Freitas, Daniel Brito",
      "De Medeiros, Jose Renan",
      "Delgado-Mena, Elisa",
      "Figueira, Pedro",
      "Dumusque, Xavier",
      "Ehrenreich, David",
      "Lafreni\u00e8re, David",
      "Lovis, Christophe",
      "Malo, Lison",
      "Melo, Claudio",
      "Mordasini, Christoph",
      "Pepe, Francesco",
      "Rebolo, Rafael",
      "Rowe, Jason",
      "Santos, Nuno C.",
      "S\u00e9gransan, Damien",
      "Udry, St\u00e9phane",
      "Valencia, Diana",
      "Wade, Gregg",
      "Abreu, Manuel",
      "Aguiar, Jos\u00e9 L. A.",
      "Al Moulla, Khaled",
      "Allain, Guillaume",
      "Allart, Romain",
      "Arial, Tomy",
      "Auger, Hugues",
      "Bazinet, Luc",
      "Blind, Nicolas",
      "Bohlender, David",
      "Boisse, Isabelle",
      "Boucher, Anne",
      "Bourrier, Vincent",
      "Bovay, S\u00e9bastien",
      "Broeg, Christopher",
      "Brousseau, Denis",
      "Cabral, Alexandre",
      "Carmona, Andres",
      "Carteret, Yann",
      "Challita, Zalpha",
      "Chazelas, Bruno",
      "Coelho, Jo\u00e3o",
      "Cointepas, Marion",
      "Conod, Uriel",
      "Cristo, Eduardo",
      "Costa Silva, Ana Rita",
      "Darveau-Bernier, Antoine",
      "Dauplaise, Laurie",
      "Delisle, Jean-Baptiste",
      "de Lima Gomes, Roseane",
      "Forveille, Thierry",
      "Frensch, Yolanda G. C.",
      "Gracia T\u00e9mich, F\u00e9lix",
      "Fontinele, Dasaev O.",
      "Gagn\u00e9, Jonathan",
      "Genest, Fr\u00e9d\u00e9ric",
      "Genolet, Ludovic",
      "Gomes da Silva, Jo\u00e3o",
      "Grieves, Nolan",
      "Hernandez, Olivier",
      "Hobson, Melissa J.",
      "Hoeijmakers, H. Jens",
      "Hubin, Norbert",
      "Jahandar, Farbod",
      "Jayawardhana, Ray",
      "K\u00e4ufl, Hans-Ulrich",
      "Kerley, Dan",
      "Kolb, Johann",
      "Krishnamurthy, Vigneshwaran",
      "Kung, Benjamin",
      "L'Heureux, Alexandrine",
      "Larue, Pierre",
      "Leath, Henry",
      "Lim, Olivia",
      "Lo Curto, Gaspare",
      "Martins, Allan M.",
      "Matthews, Jaymie",
      "Mayer, Jean-S\u00e9bastien",
      "Messias, Yuri S.",
      "Metchev, Stan",
      "Moranta, Leslie",
      "Mounzer, Dany",
      "Nari, Nicola",
      "Nielsen, Louise D.",
      "Osborn, Ares",
      "Ouellet, Mathieu",
      "Otegi, Jon",
      "Parc, L\u00e9na",
      "Pasquini, Luca",
      "Passegger, Vera M.",
      "Pelletier, Stefan",
      "Peroux, C\u00e9line",
      "Piaulet-Ghorayeb, Caroline",
      "Plotnykov, Mykhaylo",
      "Pompei, Emanuela",
      "Poulin-Girard, Anne-Sophie",
      "Rasilla, Jos\u00e9 Luis",
      "Reshetov, Vladimir",
      "Saint-Antoine, Jonathan",
      "Sarajlic, Mirsad",
      "Saviane, Ivo",
      "Schnell, Robin",
      "Segovia, Alex",
      "Seidel, Julia",
      "Silber, Armin",
      "Sinclair, Peter",
      "Sordet, Michael",
      "Sosnowska, Danuta",
      "Srivastava, Avidaan",
      "Teixeira, M\u00e1rcio A.",
      "Thibault, Simon",
      "Vall\u00e9e, Philippe",
      "Vaulato, Valentina",
      "Wardenier, Joost P.",
      "Wehbe, Bachar",
      "Weisserman, Drew",
      "Wevers, Ivan",
      "Wildi, Fran\u00e7ois",
      "Yariv, Vincent",
      "Zins, G\u00e9rard"
    ],
    "year": "2025",
    "pubdate": "2025-07-00",
    "doi": [
      "10.1051/0004-6361/202553728",
      "10.48550/arXiv.2507.21751"
    ],
    "title": "Diving into the planetary system of Proxima with NIRPS: Breaking the metre per second barrier in the infrared",
    "pub": "Astronomy and Astrophysics",
    "volume": "700",
    "page": "A11",
    "citations": 10,
    "url": "https://ui.adsabs.harvard.edu/abs/2025A&A...700A..11S"
  },
  {
    "doctype": "article",
    "authors": [
      "Doyon, R.",
      "Bouchy, F.",
      "Pepe, F.",
      "Melo, C.",
      "Artigau, \u00c9.",
      "Malo, L.",
      "Wildi, F.",
      "Baron, F.",
      "Delfosse, X.",
      "Renan De Medeiros, J.",
      "Gonz\u00e1lez Hern\u00e1ndez, J. I.",
      "Santos, N. C.",
      "Wade, G.",
      "Allart, R.",
      "Al Moulla, K.",
      "Blind, N.",
      "Cadieux, C.",
      "Canto Martins, B. L.",
      "Cook, N. J.",
      "Dumusque, X.",
      "Frensch, Y.",
      "Genest, F.",
      "Grieves, N.",
      "Lo Curto, G.",
      "Lovis, C.",
      "Mignon, L.",
      "Nielsen, L. D.",
      "Poulin-Girard, A.-S.",
      "Rasilla, J. L.",
      "Rebolo, R.",
      "Reshetov, V.",
      "Sosnowska, D.",
      "Sordet, M.",
      "Saint-Antoine, J.",
      "Su\u00e1rez Mascare\u00f1o, A.",
      "Thibault, S.",
      "Vall\u00e9e, P.",
      "Vandal, T.",
      "Abreu, M.",
      "Aguiar, J. L. A.",
      "Allain, G.",
      "Arial, T.",
      "Auger, H.",
      "Barros, S. C. C.",
      "Bazinet, L.",
      "Benneke, B.",
      "Bonfils, X.",
      "Boucher, A.",
      "Bourrier, V.",
      "Bovay, S.",
      "Broeg, C.",
      "Brousseau, D.",
      "Bruniquel, V.",
      "Bryan, M.",
      "Cabral, A.",
      "Carmona, A.",
      "Carteret, Y.",
      "Challita, Z.",
      "Chazelas, B.",
      "Cloutier, R.",
      "Coelho, J.",
      "Cointepas, M.",
      "Conod, U.",
      "Cowan, N. B.",
      "Cristo, E.",
      "Gomes da Silva, J.",
      "Dauplaise, L.",
      "Darveau-Bernier, A.",
      "de Lima Gomes, R.",
      "Brito de Freitas, D.",
      "Delgado-Mena, E.",
      "Delisle, J.-B.",
      "Ehrenreich, D.",
      "Faria, J.",
      "Figueira, P.",
      "Fontinele, D. O.",
      "Forveille, T.",
      "Gagn\u00e9, J.",
      "Genolet, L.",
      "Gracia T\u00e9mich, F.",
      "Hernandez, O.",
      "Hobson, M. J.",
      "Hoeijmakers, J.",
      "Hubin, N.",
      "Jahandar, F.",
      "Jayawardhana, R.",
      "K\u00e4ufl, H.-U.",
      "Kerley, D.",
      "Kolb, J.",
      "Krishnamurthy, V.",
      "Lafreni\u00e8re, D.",
      "Lamontagne, P.",
      "Larue, P.",
      "Leath, H.",
      "L'Heureux, A.",
      "de Castro Le\u00e3o, I.",
      "Lim, O.",
      "Martins, A. M.",
      "Matthews, J.",
      "Mayer, J.-S.",
      "Messias, Y. S.",
      "Metchev, S.",
      "Moranta, L.",
      "Mordasini, C.",
      "Mounzer, D.",
      "Nari, N.",
      "Osborn, A.",
      "Ouellet, M.",
      "Otegi, J.",
      "Parc, L.",
      "Pasquini, L.",
      "Passegger, V. M.",
      "Pelletier, S.",
      "Peroux, C.",
      "Piaulet-Ghorayeb, C.",
      "Plotnykov, M.",
      "Pompei, E.",
      "Rowe, J.",
      "Sarajlic, M.",
      "Segovia, A.",
      "Seidel, J.",
      "S\u00e9gransan, D.",
      "Schnell, R.",
      "Costa Silva, A. R.",
      "Srivastava, A.",
      "Stefanov, A. K.",
      "Teixeira, M. A.",
      "Udry, S.",
      "Valencia, D.",
      "Vaulato, V.",
      "Wardenier, J. P.",
      "Wehbe, B.",
      "Weisserman, D.",
      "Wevers, I.",
      "Yariv, V.",
      "Zins, G."
    ],
    "year": "2025",
    "pubdate": "2025-03-00",
    "doi": [
      "10.18727/0722-6691/5379"
    ],
    "title": "NIRPS Joins HARPS: Setting New Standards at Infrared Wavelengths",
    "pub": "The Messenger",
    "volume": "194",
    "page": "13",
    "citations": 0,
    "url": "https://ui.adsabs.harvard.edu/abs/2025Msngr.194...13D"
  },
  {
    "doctype": "article",
    "authors": [
      "Desli\u00e8res, Ariane",
      "Cadieux, Charles",
      "Doyon, Ren\u00e9",
      "Artigau, \u00c9tienne",
      "Cook, Neil J.",
      "Fontanive, Cl\u00e9mence",
      "Vandal, Thomas"
    ],
    "year": "2025",
    "pubdate": "2025-03-00",
    "doi": [
      "10.3847/1538-3881/ada77a"
    ],
    "title": "The Gl 229 System Revisited with the Line-by-line Framework: Planetary Signals Now Appear as Stellar Activity Ghosts",
    "pub": "The Astronomical Journal",
    "volume": "169",
    "page": "182",
    "citations": 1,
    "url": "https://ui.adsabs.harvard.edu/abs/2025AJ....169..182D"
  },
  {
    "doctype": "article",
    "authors": [
      "Albert, Lo\u00efc",
      "Leggett, Sandy K.",
      "Calissendorff, Per",
      "Vandal, Thomas",
      "Kirkpatrick, J. Davy",
      "Bardalez Gagliuffi, Daniella C.",
      "De Furio, Matthew",
      "Meyer, Michael",
      "Beichman, Charles A.",
      "Burgasser, Adam J.",
      "Cushing, Michael C.",
      "Faherty, Jacqueline Kelly",
      "Fontanive, Cl\u00e9mence",
      "Gelino, Christopher R.",
      "Gizis, John E.",
      "Greenbaum, Alexandra Z.",
      "Martinache, Frantz",
      "N'Diaye, Mamadou",
      "Pope, Benjamin J. S.",
      "Roellig, Thomas L.",
      "Sahlmann, Johannes",
      "Sivaramakrishnan, Anand",
      "Ygouf, Marie"
    ],
    "year": "2025",
    "pubdate": "2025-03-00",
    "doi": [
      "10.3847/1538-3881/adadf9",
      "10.48550/arXiv.2501.14100"
    ],
    "title": "JWST 1.5 \u03bcm and 4.8 \u03bcm Photometry of Y Dwarfs",
    "pub": "The Astronomical Journal",
    "volume": "169",
    "page": "163",
    "citations": 3,
    "url": "https://ui.adsabs.harvard.edu/abs/2025AJ....169..163A"
  },
  {
    "doctype": "article",
    "authors": [
      "Blakely, Dori",
      "Johnstone, Doug",
      "Cugno, Gabriele",
      "Sivaramakrishnan, Anand",
      "Tuthill, Peter",
      "Dong, Ruobing",
      "Pope, Benjamin J. S.",
      "Albert, Lo\u00efc",
      "Charles, Max",
      "Cooper, Rachel A.",
      "De Furio, Matthew",
      "Desdoigts, Louis",
      "Doyon, Ren\u00e9",
      "Francis, Logan",
      "Greenbaum, Alexandra Z.",
      "Lafreni\u00e8re, David",
      "Lloyd, James P.",
      "Meyer, Michael R.",
      "Pueyo, Laurent",
      "Ray, Shrishmoy",
      "S\u00e1nchez-Berm\u00fadez, Joel",
      "Soulain, Anthony",
      "Thatte, Deepashri",
      "Thompson, William",
      "Vandal, Thomas"
    ],
    "year": "2025",
    "pubdate": "2025-03-00",
    "doi": [
      "10.3847/1538-3881/ad9b94",
      "10.48550/arXiv.2404.13032"
    ],
    "title": "The James Webb Interferometer: Space-based Interferometric Detections of PDS 70 b and c at 4.8 \u03bcm",
    "pub": "The Astronomical Journal",
    "volume": "169",
    "page": "137",
    "citations": 17,
    "url": "https://ui.adsabs.harvard.edu/abs/2025AJ....169..137B"
  },
  {
    "doctype": "inproceedings",
    "authors": [
      "Cooper, Rachel A.",
      "Thatte, Deepashri",
      "Sivaramakrishnan, Anand",
      "Albert, L\u00f6ic",
      "Cook, Neil J.",
      "Kammerer, Jens",
      "Martel, Andr\u00e9 R.",
      "Sanchez-Bermudez, Joel",
      "Soulain, Anthony",
      "Vandal, Thomas",
      "Volk, Kevin"
    ],
    "year": "2024",
    "pubdate": "2024-08-00",
    "doi": [
      "10.1117/12.3019153"
    ],
    "title": "Commissioning and calibration of the JWST aperture masking interferometry mode",
    "pub": "Optical and Infrared Interferometry and Imaging IX",
    "volume": "13095",
    "page": "130952R",
    "citations": 0,
    "url": "https://ui.adsabs.harvard.edu/abs/2024SPIE13095E..2RC"
  },
  {
    "doctype": "inproceedings",
    "authors": [
      "Malo, Lison",
      "Baron, Fr\u00e9d\u00e9rique",
      "Poulin-Girard, Anne-Sophie",
      "Vall\u00e9e, Philippe",
      "St-Antoine, Jonathan",
      "Brousseau, Denis",
      "Auger, Hugues",
      "Reshetov, Vladimir",
      "Wildi, Fran\u00e7ois",
      "Sordet, Micha\u00ebl.",
      "Artigau, \u00c9tienne",
      "Doyon, Ren\u00e9",
      "Thibault, Simon",
      "Bouchy, Fran\u00e7ois",
      "Cook, Neil J.",
      "Frensch, Yolanda",
      "Lo Curto, Gaspare",
      "Zins, G\u00e9rard",
      "Sosnowska, Danuta",
      "Wevers, Ivan",
      "Kerley, Dan",
      "Allain, Guillaume",
      "Allart, Romain",
      "Hubin, Norbert",
      "Cadieux, Charles",
      "Carmona, Andres",
      "Challita, Zalpha",
      "Grieves, Nolan",
      "Hernandez, Olivier",
      "Vandal, Thomas",
      "Blind, Nicolas",
      "Mignon, Lucile",
      "Nielsen, Louise",
      "Pepe, Francesco",
      "Dumusque, Xavier",
      "Lovis, Christophe",
      "Canto Martins, Bruno L.",
      "de Medeiros, Jos\u00e9 Renan",
      "Delfosse, Xavier",
      "Santos, Nuno",
      "Gonz\u00e1lez-Hern\u00e1ndez, Jonay I.",
      "Rebolo, Rafael",
      "Wade, Gregg",
      "Abreu, Manuel",
      "Barros, Susana",
      "Bazinet, Luc",
      "Boisse, Isabelle",
      "Bonfils, Xavier",
      "Bourrier, Vincent",
      "Bovay, S\u00e9bastien",
      "Broeg, Christopher",
      "Bruniquel, Vincent",
      "Cabral, Alexandre",
      "Carteret, Yann",
      "Chazelas, Bruno",
      "Cloutier, Ryan",
      "Coelho, Jo\u00e3o.",
      "Cointepas, Marion",
      "Conod, Uriel",
      "Cowan, Nicolas",
      "Cristo, Eduardo",
      "Gomes da Silva, Joao",
      "Dauplaise, Laurie",
      "de Lima Gomes, Roseane",
      "Delgado-Mena, Elisa",
      "Ehrenreich, David",
      "Faria, Joao",
      "Figueira, Pedro",
      "Forveille, Thierry",
      "Gagne, Jonathan",
      "Genest, Frederic",
      "Genolet, Ludovic",
      "Gracia T\u00e9mich, F\u00e9lix",
      "Hobson, Melissa J.",
      "Hoeijmakers, Jens",
      "Krishnamurthy, Vigneshwaran",
      "Lafreniere, David",
      "Lamontagne, Pierrot",
      "Larue, Pierre",
      "Leath, Henry",
      "Le\u00e3o, Izan C.",
      "Lim, Olivia",
      "Martins, Allan M.",
      "Melo, Claudio",
      "Messias, Yuri S.",
      "Moranta, Leslie",
      "Mordasini, Christoph",
      "Al Moulla, Khaled",
      "Mounzer, Dany",
      "L'Heureux, Alexandrine",
      "Nari, Nicola",
      "Osborn, Ares",
      "Parc, Lena",
      "Pasquini, Luca",
      "Passegger, Vera M.",
      "Pelletier, Stefan",
      "Peroux, Celine",
      "Piaulet, Caroline",
      "Plotnykov, Mykhaylo",
      "Rasilla, Jos\u00e9 Luis",
      "Sarajlic, Mirsad",
      "Segovia, Alex",
      "Seidel, Julia",
      "Segransan, Damien",
      "Costa Silva, Ana Rita",
      "Srivastava, Avidaan",
      "Stefanov, Atanas K.",
      "Su\u00e1rez Mascare\u00f1o, Alejandro",
      "Teixeira, Marcio A.",
      "Udry, Stephane",
      "Valencia, Diana",
      "Vaulato, Valentina",
      "Wardenier, Joost P.",
      "Wehb\u00e9, Bachar",
      "Weisserman, Drew",
      "Kung, Benjamin",
      "Boucher, Anne",
      "Schnell, Robin",
      "Silber, Armin",
      "Saviane, Ivo",
      "Pompei, Emanuela",
      "Sinclaire, Peter"
    ],
    "year": "2024",
    "pubdate": "2024-07-00",
    "doi": [
      "10.1117/12.3020168"
    ],
    "title": "NIRPS near-infrared spectrograph: AITV phase at ESO3.6m/La Silla",
    "pub": "Ground-based and Airborne Instrumentation for Astronomy X",
    "volume": "13096",
    "page": "1309646",
    "citations": 0,
    "url": "https://ui.adsabs.harvard.edu/abs/2024SPIE13096E..46M"
  },
  {
    "doctype": "inproceedings",
    "authors": [
      "Artigau, \u00c9tienne",
      "Bouchy, Fran\u00e7ois",
      "Doyon, Ren\u00e9",
      "Baron, Fr\u00e9d\u00e9rique",
      "Malo, Lison",
      "Wildi, Fran\u00e7ois",
      "Pepe, Franceso",
      "Cook, Neil J.",
      "Thibault, Simon",
      "Reshetov, Vladimir",
      "Dumusque, Xavier",
      "Lovis, Christophe",
      "Sosnowska, Danuta",
      "Canto Martins, Bruno L.",
      "De Medeiros, Jose Renan",
      "Delfosse, Xavier",
      "Santos, Nuno",
      "Rebolo, Rafael",
      "Abreu, Manuel",
      "Allain, Guillaume",
      "Allart, Romain",
      "Auger, Hugues",
      "Barros, Susana",
      "Bazinet, Luc",
      "Blind, Nicolas",
      "Boisse, Isabelle",
      "Bonfils, Xavier",
      "Bourrier, Vincent",
      "Bovay, S\u00e9bastien",
      "Broeg, Christopher",
      "Brousseau, Denis",
      "Bruniquel, Vincent",
      "Cabral, Alexandre",
      "Cadieux, Charles",
      "Carmona, Andres",
      "Carteret, Yann",
      "Challita, Zalpha",
      "Chazelas, Bruno",
      "Cloutier, Ryan",
      "Coelho, Jo\u00e3o. M.",
      "Cointepas, Marion",
      "Conod, Uriel",
      "Cowan, Nicolas",
      "Cristo, Eduardo",
      "Gomes da Silva, Jo\u00e3o.",
      "Dauplaise, Laurie",
      "Lima Gomes, Roseane",
      "Delgado-Mena, Elisa",
      "Ehrenreich, David",
      "Faria, Jo\u00e3o.",
      "Figueira, Pedro",
      "Forveille, Thierry",
      "Frensch, Yolanda",
      "Gagn\u00e9, Jonathan",
      "Genest, Fr\u00e9d\u00e9ric",
      "Genolet, Ludovic",
      "Gonz\u00e1lez Hern\u00e1ndez, Jonay I.",
      "Gracia Temich, Felix",
      "Grieves, Nolan",
      "Hernandez, Olivier",
      "Hobson, Melissa J.",
      "Hoeijmakers, Jens",
      "Kerley, Dan",
      "Krishnamurthy, Vigneshwaran",
      "Lafreni\u00e8re, David",
      "Lamontagne, Pierrot",
      "Larue, Pierre",
      "Leaf, Henry",
      "Le\u00e3o, Izan C.",
      "Lim, Olivia",
      "Lo Curto, Gaspare",
      "Martins, Allan M.",
      "Melo, Claudio",
      "Messias, Yuri",
      "Mignon, Lucile",
      "Moranta, Leslie",
      "Mordasini, Christoph",
      "Al Moulla, Khaled",
      "Mounzer, Dany",
      "L'Heureux, Alexandrine",
      "Nari, Nicola",
      "Nielsen, Louise",
      "Osborn, Ares",
      "Parc, Lena",
      "Pasquini, Luca",
      "Passegger, Vera",
      "Pelletier, Stefan",
      "Peroux, C\u00e9line",
      "Piaulet, Caroline",
      "Plotnykov, Mykhaylo",
      "Poulin-Girard, Anne-Sophie",
      "Rasilla, Jos\u00e9 Luis",
      "Saint-Antoine, Jonathan",
      "Sarajic, Mirsad",
      "Segovia, Alex",
      "Seidel, Julia V.",
      "S\u00e9gransan, Damien",
      "Silva, Ana Rita",
      "Srivastava, Avidaan",
      "Stefanov, Atanas K.",
      "Su\u00e1rez Mascare\u00f1o, Alejandro",
      "Sordet, Michael",
      "Teixeira, M\u00e1rcio A.",
      "Udry, Sf\u00e9phane",
      "Valencia, Diana",
      "Vall\u00e9e, Philippe",
      "Vandal, Thomas",
      "Vaulato, Valentina",
      "Wade, Gregg",
      "Wardenier, Joost P.",
      "Wehb\u00e9, Bachar",
      "Weisserman, Drew",
      "Wevers, Ivan",
      "Zins, G\u00e9rard"
    ],
    "year": "2024",
    "pubdate": "2024-07-00",
    "doi": [
      "10.1117/12.3018994",
      "10.48550/arXiv.2406.08304"
    ],
    "title": "NIRPS first light and early science: breaking the 1 m/s RV precision barrier at infrared wavelengths",
    "pub": "Ground-based and Airborne Instrumentation for Astronomy X",
    "volume": "13096",
    "page": "130960C",
    "citations": 4,
    "url": "https://ui.adsabs.harvard.edu/abs/2024SPIE13096E..0CA"
  },
  {
    "doctype": "article",
    "authors": [
      "Jahandar, Farbod",
      "Doyon, Ren\u00e9",
      "Artigau, \u00c9tienne",
      "Cook, Neil J.",
      "Cadieux, Charles",
      "Lafreni\u00e8re, David",
      "Forveille, Thierry",
      "Donati, Jean-Fran\u00e7ois",
      "Fouqu\u00e9, Pascal",
      "Carmona, Andr\u00e9s",
      "Cloutier, Ryan",
      "Cristofari, Paul",
      "Gaidos, Eric",
      "Gomes da Silva, Jo\u00e3o",
      "Malo, Lison",
      "Martioli, Eder",
      "do Nascimento, J.-D.",
      "Pelletier, Stefan",
      "Vandal, Thomas",
      "Venn, Kim"
    ],
    "year": "2024",
    "pubdate": "2024-05-00",
    "doi": [
      "10.3847/1538-4357/ad3063",
      "10.48550/arXiv.2310.12125"
    ],
    "title": "Comprehensive High-resolution Chemical Spectroscopy of Barnard's Star with SPIRou",
    "pub": "The Astrophysical Journal",
    "volume": "966",
    "page": "56",
    "citations": 16,
    "url": "https://ui.adsabs.harvard.edu/abs/2024ApJ...966...56J"
  },
  {
    "doctype": "article",
    "authors": [
      "Moutou, C.",
      "Delfosse, X.",
      "Petit, A. C.",
      "Donati, J.-F.",
      "Artigau, E.",
      "Fouqu\u00e9, P.",
      "Carmona, A.",
      "Ould-Elhkim, M.",
      "Arnold, L.",
      "Cook, N. J.",
      "Cadieux, C.",
      "Bellotti, S.",
      "Boisse, I.",
      "Bouchy, F.",
      "Charpentier, P.",
      "Cort\u00e9s-Zuleta, P.",
      "Doyon, R.",
      "H\u00e9brard, G.",
      "Martioli, E.",
      "Morin, J.",
      "Vandal, T."
    ],
    "year": "2023",
    "pubdate": "2023-10-00",
    "doi": [
      "10.1051/0004-6361/202346813",
      "10.48550/arXiv.2307.11569"
    ],
    "title": "Characterizing planetary systems with SPIRou: M-dwarf planet-search survey and the multiplanet systems GJ 876 and GJ 1148",
    "pub": "Astronomy and Astrophysics",
    "volume": "678",
    "page": "A207",
    "citations": 10,
    "url": "https://ui.adsabs.harvard.edu/abs/2023A&A...678A.207M"
  },
  {
    "doctype": "article",
    "authors": [
      "Doyon, Ren\u00e9",
      "Willott, Chris J.",
      "Hutchings, John B.",
      "Sivaramakrishnan, Anand",
      "Albert, Lo\u00efc",
      "Lafreni\u00e8re, David",
      "Rowlands, Neil",
      "Bego\u00f1a Vila, M.",
      "Martel, Andr\u00e9 R.",
      "LaMassa, Stephanie",
      "Aldridge, David",
      "Artigau, \u00c9tienne",
      "Cameron, Peter",
      "Chayer, Pierre",
      "Cook, Neil J.",
      "Cooper, Rachel A.",
      "Darveau-Bernier, Antoine",
      "Dupuis, Jean",
      "Earnshaw, Colin",
      "Espinoza, N\u00e9stor",
      "Filippazzo, Joseph C.",
      "Fullerton, Alexander W.",
      "Gaudreau, Daniel",
      "Gawlik, Roman",
      "Goudfrooij, Paul",
      "Haley, Craig",
      "Kammerer, Jens",
      "Kendall, David",
      "Lambros, Scott D.",
      "Ignat, Luminita Ilinca",
      "Maszkiewicz, Michael",
      "McColgan, Ashley",
      "Morishita, Takahiro",
      "Ouellette, Nathalie N.-Q.",
      "Pacifici, Camilla",
      "Philippi, Natasha",
      "Radica, Michael",
      "Ravindranath, Swara",
      "Rowe, Jason",
      "Roy, Arpita",
      "Roy, Niladri",
      "Saad, Karl",
      "Sohn, Sangmo Tony",
      "Talens, Geert Jan",
      "Touahri, Driss",
      "Thatte, Deepashri",
      "Taylor, Joanna M.",
      "Vandal, Thomas",
      "Volk, Kevin",
      "Wander, Michel",
      "Warner, Gerald",
      "Zheng, Sheng-Hai",
      "Zhou, Julia",
      "Abraham, Roberto",
      "Beaulieu, Mathilde",
      "Benneke, Bj\u00f6rn",
      "Ferrarese, Laura",
      "Jayawardhana, Ray",
      "Johnstone, Doug",
      "Kaltenegger, Lisa",
      "Meyer, Michael R.",
      "Pipher, Judy L.",
      "Rameau, Julien",
      "Rieke, Marcia",
      "Salhi, Salma",
      "Sawicki, Marcin"
    ],
    "year": "2023",
    "pubdate": "2023-09-00",
    "doi": [
      "10.1088/1538-3873/acd41b",
      "10.48550/arXiv.2306.03277"
    ],
    "title": "The Near Infrared Imager and Slitless Spectrograph for the James Webb Space Telescope. I. Instrument Overview and In-flight Performance",
    "pub": "Publications of the Astronomical Society of the Pacific",
    "volume": "135",
    "page": "098001",
    "citations": 83,
    "url": "https://ui.adsabs.harvard.edu/abs/2023PASP..135i8001D"
  },
  {
    "doctype": "article",
    "authors": [
      "Cort\u00e9s-Zuleta, P.",
      "Boisse, I.",
      "Klein, B.",
      "Martioli, E.",
      "Cristofari, P. I.",
      "Antoniadis-Karnavas, A.",
      "Donati, J.-F.",
      "Delfosse, X.",
      "Cadieux, C.",
      "Heidari, N.",
      "Artigau, \u00c9.",
      "Bellotti, S.",
      "Bonfils, X.",
      "Carmona, A.",
      "Cook, N. J.",
      "D\u00edaz, R. F.",
      "Doyon, R.",
      "Fouqu\u00e9, P.",
      "Moutou, C.",
      "Petit, P.",
      "Vandal, T.",
      "Acu\u00f1a, L.",
      "Arnold, L.",
      "Astudillo-Defru, N.",
      "Bourrier, V.",
      "Bouchy, F.",
      "Cloutier, R.",
      "Dalal, S.",
      "Deleuil, M.",
      "Demangeon, O. D. S.",
      "Dumusque, X.",
      "Forveille, T.",
      "Gomes da Silva, J.",
      "Hara, N.",
      "H\u00e9brard, G.",
      "Hoyer, S.",
      "Hussain, G.",
      "Kiefer, F.",
      "Morin, J.",
      "Santerne, A.",
      "Santos, N. C.",
      "Segransan, D.",
      "Stalport, M.",
      "Udry, S."
    ],
    "year": "2023",
    "pubdate": "2023-05-00",
    "doi": [
      "10.1051/0004-6361/202245131",
      "10.48550/arXiv.2301.10614"
    ],
    "title": "Optical and near-infrared stellar activity characterization of the early M dwarf Gl 205 with SOPHIE and SPIRou",
    "pub": "Astronomy and Astrophysics",
    "volume": "673",
    "page": "A14",
    "citations": 17,
    "url": "https://ui.adsabs.harvard.edu/abs/2023A&A...673A..14C"
  },
  {
    "doctype": "article",
    "authors": [
      "Calissendorff, Per",
      "De Furio, Matthew",
      "Meyer, Michael",
      "Albert, Lo\u00efc",
      "Aganze, Christian",
      "Ali-Dib, Mohamad",
      "Bardalez Gagliuffi, Daniella C.",
      "Baron, Frederique",
      "Beichman, Charles A.",
      "Burgasser, Adam J.",
      "Cushing, Michael C.",
      "Faherty, Jacqueline Kelly",
      "Fontanive, Cl\u00e9mence",
      "Gelino, Christopher R.",
      "Gizis, John E.",
      "Greenbaum, Alexandra Z.",
      "Kirkpatrick, J. Davy",
      "Leggett, Sandy K.",
      "Martinache, Frantz",
      "Mary, David",
      "N'Diaye, Mamadou",
      "Pope, Benjamin J. S.",
      "Roellig, Thomas",
      "Sahlmann, Johannes",
      "Sivaramakrishnan, Anand",
      "Thorngren, Daniel Peter",
      "Ygouf, Marie",
      "Vandal, Thomas"
    ],
    "year": "2023",
    "pubdate": "2023-04-00",
    "doi": [
      "10.3847/2041-8213/acc86d",
      "10.48550/arXiv.2303.16923"
    ],
    "title": "JWST/NIRCam Discovery of the First Y+Y Brown Dwarf Binary: WISE J033605.05-014350.4",
    "pub": "The Astrophysical Journal",
    "volume": "947",
    "page": "L30",
    "citations": 24,
    "url": "https://ui.adsabs.harvard.edu/abs/2023ApJ...947L..30C"
  },
  {
    "doctype": "article",
    "authors": [
      "Rigby, Jane",
      "Perrin, Marshall",
      "McElwain, Michael",
      "Kimble, Randy",
      "Friedman, Scott",
      "Lallo, Matt",
      "Doyon, Ren\u00e9",
      "Feinberg, Lee",
      "Ferruit, Pierre",
      "Glasse, Alistair",
      "Rieke, Marcia",
      "Rieke, George",
      "Wright, Gillian",
      "Willott, Chris",
      "Colon, Knicole",
      "Milam, Stefanie",
      "Neff, Susan",
      "Stark, Christopher",
      "Valenti, Jeff",
      "Abell, Jim",
      "Abney, Faith",
      "Abul-Huda, Yasin",
      "Acton, D. Scott",
      "Adams, Evan",
      "Adler, David",
      "Aguilar, Jonathan",
      "Ahmed, Nasif",
      "Albert, Lo\u00efc",
      "Alberts, Stacey",
      "Aldridge, David",
      "Allen, Marsha",
      "Altenburg, Martin",
      "\u00c1lvarez-M\u00e1rquez, Javier",
      "Alves de Oliveira, Catarina",
      "Andersen, Greg",
      "Anderson, Harry",
      "Anderson, Sara",
      "Argyriou, Ioannis",
      "Armstrong, Amber",
      "Arribas, Santiago",
      "Artigau, Etienne",
      "Arvai, Amanda",
      "Atkinson, Charles",
      "Bacon, Gregory",
      "Bair, Thomas",
      "Banks, Kimberly",
      "Barrientes, Jaclyn",
      "Barringer, Bruce",
      "Bartosik, Peter",
      "Bast, William",
      "Baudoz, Pierre",
      "Beatty, Thomas",
      "Bechtold, Katie",
      "Beck, Tracy",
      "Bergeron, Eddie",
      "Bergkoetter, Matthew",
      "Bhatawdekar, Rachana",
      "Birkmann, Stephan",
      "Blazek, Ronald",
      "Blome, Claire",
      "Boccaletti, Anthony",
      "B\u00f6ker, Torsten",
      "Boia, John",
      "Bonaventura, Nina",
      "Bond, Nicholas",
      "Bosley, Kari",
      "Boucarut, Ray",
      "Bourque, Matthew",
      "Bouwman, Jeroen",
      "Bower, Gary",
      "Bowers, Charles",
      "Boyer, Martha",
      "Bradley, Larry",
      "Brady, Greg",
      "Braun, Hannah",
      "Breda, David",
      "Bresnahan, Pamela",
      "Bright, Stacey",
      "Britt, Christopher",
      "Bromenschenkel, Asa",
      "Brooks, Brian",
      "Brooks, Keira",
      "Brown, Bob",
      "Brown, Matthew",
      "Brown, Patricia",
      "Bunker, Andy",
      "Burger, Matthew",
      "Bushouse, Howard",
      "Cale, Steven",
      "Cameron, Alex",
      "Cameron, Peter",
      "Canipe, Alicia",
      "Caplinger, James",
      "Caputo, Francis",
      "Cara, Mihai",
      "Carey, Larkin",
      "Carniani, Stefano",
      "Carrasquilla, Maria",
      "Carruthers, Margaret",
      "Case, Michael",
      "Catherine, Riggs",
      "Chance, Don",
      "Chapman, George",
      "Charlot, St\u00e9phane",
      "Charlow, Brian",
      "Chayer, Pierre",
      "Chen, Bin",
      "Cherinka, Brian",
      "Chichester, Sarah",
      "Chilton, Zack",
      "Chonis, Taylor",
      "Clampin, Mark",
      "Clark, Charles",
      "Clark, Kerry",
      "Coe, Dan",
      "Coleman, Benee",
      "Comber, Brian",
      "Comeau, Tom",
      "Connolly, Dennis",
      "Cooper, James",
      "Cooper, Rachel",
      "Coppock, Eric",
      "Correnti, Matteo",
      "Cossou, Christophe",
      "Coulais, Alain",
      "Coyle, Laura",
      "Cracraft, Misty",
      "Curti, Mirko",
      "Cuturic, Steven",
      "Davis, Katherine",
      "Davis, Michael",
      "Dean, Bruce",
      "DeLisa, Amy",
      "deMeester, Wim",
      "Dencheva, Nadia",
      "Dencheva, Nadezhda",
      "DePasquale, Joseph",
      "Deschenes, Jeremy",
      "Hunor Detre, \u00d6rs",
      "Diaz, Rosa",
      "Dicken, Dan",
      "DiFelice, Audrey",
      "Dillman, Matthew",
      "Dixon, William",
      "Doggett, Jesse",
      "Donaldson, Tom",
      "Douglas, Rob",
      "DuPrie, Kimberly",
      "Dupuis, Jean",
      "Durning, John",
      "Easmin, Nilufar",
      "Eck, Weston",
      "Edeani, Chinwe",
      "Egami, Eiichi",
      "Ehrenwinkler, Ralf",
      "Eisenhamer, Jonathan",
      "Eisenhower, Michael",
      "Elie, Michelle",
      "Elliott, James",
      "Elliott, Kyle",
      "Ellis, Tracy",
      "Engesser, Michael",
      "Espinoza, Nestor",
      "Etienne, Odessa",
      "Etxaluze, Mireya",
      "Falini, Patrick",
      "Feeney, Matthew",
      "Ferry, Malcolm",
      "Filippazzo, Joseph",
      "Fincham, Brian",
      "Fix, Mees",
      "Flagey, Nicolas",
      "Florian, Michael",
      "Flynn, Jim",
      "Fontanella, Erin",
      "Ford, Terrance",
      "Forshay, Peter",
      "Fox, Ori",
      "Franz, David",
      "Fu, Henry",
      "Fullerton, Alexander",
      "Galkin, Sergey",
      "Galyer, Anthony",
      "Garc\u00eda Mar\u00edn, Macarena",
      "Gardner, Jonathan P.",
      "Gardner, Lisa",
      "Garland, Dennis",
      "Garrett, Bruce",
      "Gasman, Danny",
      "Gaspar, Andras",
      "Gaudreau, Daniel",
      "Gauthier, Peter",
      "Geers, Vincent",
      "Geithner, Paul",
      "Gennaro, Mario",
      "Giardino, Giovanna",
      "Girard, Julien",
      "Giuliano, Mark",
      "Glassmire, Kirk",
      "Glauser, Adrian",
      "Glazer, Stuart",
      "Godfrey, John",
      "Golimowski, David",
      "Gollnitz, David",
      "Gong, Fan",
      "Gonzaga, Shireen",
      "Gordon, Michael",
      "Gordon, Karl",
      "Goudfrooij, Paul",
      "Greene, Thomas",
      "Greenhouse, Matthew",
      "Grimaldi, Stefano",
      "Groebner, Andrew",
      "Grundy, Timothy",
      "Guillard, Pierre",
      "Gutman, Irvin",
      "Ha, Kong Q.",
      "Haderlein, Peter",
      "Hagedorn, Andria",
      "Hainline, Kevin",
      "Haley, Craig",
      "Hami, Maryam",
      "Hamilton, Forrest",
      "Hammel, Heidi",
      "Hansen, Carl",
      "Harkins, Tom",
      "Harr, Michael",
      "Hart, Jessica",
      "Hart, Quyen",
      "Hartig, George",
      "Hashimoto, Ryan",
      "Haskins, Sujee",
      "Hathaway, William",
      "Havey, Keith",
      "Hayden, Brian",
      "Hecht, Karen",
      "Heller-Boyer, Chris",
      "Henriques, Caroline",
      "Henry, Alaina",
      "Hermann, Karl",
      "Hernandez, Scarlin",
      "Hesman, Brigette",
      "Hicks, Brian",
      "Hilbert, Bryan",
      "Hines, Dean",
      "Hoffman, Melissa",
      "Holfeltz, Sherie",
      "Holler, Bryan J.",
      "Hoppa, Jennifer",
      "Hott, Kyle",
      "Howard, Joseph M.",
      "Howard, Rick",
      "Hunter, Alexander",
      "Hunter, David",
      "Hurst, Brendan",
      "Husemann, Bernd",
      "Hustak, Leah",
      "Ilinca Ignat, Luminita",
      "Illingworth, Garth",
      "Irish, Sandra",
      "Jackson, Wallace",
      "Jahromi, Amir",
      "Jakobsen, Peter",
      "James, LeAndrea",
      "James, Bryan",
      "Januszewski, William",
      "Jenkins, Ann",
      "Jirdeh, Hussein",
      "Johnson, Phillip",
      "Johnson, Timothy",
      "Jones, Vicki",
      "Jones, Ron",
      "Jones, Danny",
      "Jones, Olivia",
      "Jordan, Ian",
      "Jordan, Margaret",
      "Jurczyk, Sarah",
      "Jurling, Alden",
      "Kaleida, Catherine",
      "Kalmanson, Phillip",
      "Kammerer, Jens",
      "Kang, Huijo",
      "Kao, Shaw-Hong",
      "Karakla, Diane",
      "Kavanagh, Patrick",
      "Kelly, Doug",
      "Kendrew, Sarah",
      "Kennedy, Herbert",
      "Kenny, Deborah",
      "Keski-kuha, Ritva",
      "Keyes, Charles",
      "Kidwell, Richard",
      "Kinzel, Wayne",
      "Kirk, Jeff",
      "Kirkpatrick, Mark",
      "Kirshenblat, Danielle",
      "Klaassen, Pamela",
      "Knapp, Bryan",
      "Knight, J. Scott",
      "Knollenberg, Perry",
      "Koehler, Robert",
      "Koekemoer, Anton",
      "Kovacs, Aiden",
      "Kulp, Trey",
      "Kumari, Nimisha",
      "Kyprianou, Mark",
      "La Massa, Stephanie",
      "Labador, Aurora",
      "Labiano, Alvaro",
      "Lagage, Pierre-Olivier",
      "Lajoie, Charles-Philippe",
      "Lallo, Matthew",
      "Lam, May",
      "Lamb, Tracy",
      "Lambros, Scott",
      "Lampenfield, Richard",
      "Langston, James",
      "Larson, Kirsten",
      "Law, David",
      "Lawrence, Jon",
      "Lee, David",
      "Leisenring, Jarron",
      "Lepo, Kelly",
      "Leveille, Michael",
      "Levenson, Nancy",
      "Levine, Marie",
      "Levy, Zena",
      "Lewis, Dan",
      "Lewis, Hannah",
      "Libralato, Mattia",
      "Lightsey, Paul",
      "Link, Miranda",
      "Liu, Lily",
      "Lo, Amy",
      "Lockwood, Alexandra",
      "Logue, Ryan",
      "Long, Chris",
      "Long, Douglas",
      "Loomis, Charles",
      "Lopez-Caniego, Marcos",
      "Lorenzo Alvarez, Jose",
      "Love-Pruitt, Jennifer",
      "Lucy, Adrian",
      "Luetzgendorf, Nora",
      "Maghami, Peiman",
      "Maiolino, Roberto",
      "Major, Melissa",
      "Malla, Sunita",
      "Malumuth, Eliot",
      "Manjavacas, Elena",
      "Mannfolk, Crystal",
      "Marrione, Amanda",
      "Marston, Anthony",
      "Martel, Andr\u00e9",
      "Maschmann, Marc",
      "Masci, Gregory",
      "Masciarelli, Michaela",
      "Maszkiewicz, Michael",
      "Mather, John",
      "McKenzie, Kenny",
      "McLean, Brian",
      "McMaster, Matthew",
      "Melbourne, Katie",
      "Mel\u00e9ndez, Marcio",
      "Menzel, Michael",
      "Merz, Kaiya",
      "Meyett, Michele",
      "Meza, Luis",
      "Miskey, Cherie",
      "Misselt, Karl",
      "Moller, Christopher",
      "Morrison, Jane",
      "Morse, Ernie",
      "Moseley, Harvey",
      "Mosier, Gary",
      "Mountain, Matt",
      "Mueckay, Julio",
      "Mueller, Michael",
      "Mullally, Susan",
      "Murphy, Jess",
      "Murray, Katherine",
      "Murray, Claire",
      "Mustelier, David",
      "Muzerolle, James",
      "Mycroft, Matthew",
      "Myers, Richard",
      "Myrick, Kaila",
      "Nanavati, Shashvat",
      "Nance, Elizabeth",
      "Nayak, Omnarayani",
      "Naylor, Bret",
      "Nelan, Edmund",
      "Nickson, Bryony",
      "Nielson, Alethea",
      "Nieto-Santisteban, Maria",
      "Nikolov, Nikolay",
      "Noriega-Crespo, Alberto",
      "O'Shaughnessy, Brian",
      "O'Sullivan, Brian",
      "Ochs, William",
      "Ogle, Patrick",
      "Oleszczuk, Brenda",
      "Olmsted, Joseph",
      "Osborne, Shannon",
      "Ottens, Richard",
      "Owens, Beverly",
      "Pacifici, Camilla",
      "Pagan, Alyssa",
      "Page, James",
      "Park, Sang",
      "Parrish, Keith",
      "Patapis, Polychronis",
      "Paul, Lee",
      "Pauly, Tyler",
      "Pavlovsky, Cheryl",
      "Pedder, Andrew",
      "Peek, Matthew",
      "Pena-Guerrero, Maria",
      "Penanen, Konstantin",
      "Perez, Yesenia",
      "Perna, Michele",
      "Perriello, Beth",
      "Phillips, Kevin",
      "Pietraszkiewicz, Martin",
      "Pinaud, Jean-Paul",
      "Pirzkal, Norbert",
      "Pitman, Joseph",
      "Piwowar, Aidan",
      "Platais, Vera",
      "Player, Danielle",
      "Plesha, Rachel",
      "Pollizi, Joe",
      "Polster, Ethan",
      "Pontoppidan, Klaus",
      "Porterfield, Blair",
      "Proffitt, Charles",
      "Pueyo, Laurent",
      "Pulliam, Christine",
      "Quirt, Brian",
      "Quispe Neira, Irma",
      "Ramos Alarcon, Rafael",
      "Ramsay, Leah",
      "Rapp, Greg",
      "Rapp, Robert",
      "Rauscher, Bernard",
      "Ravindranath, Swara",
      "Rawle, Timothy",
      "Regan, Michael",
      "Reichard, Timothy A.",
      "Reis, Carl",
      "Ressler, Michael E.",
      "Rest, Armin",
      "Reynolds, Paul",
      "Rhue, Timothy",
      "Richon, Karen",
      "Rickman, Emily",
      "Ridgaway, Michael",
      "Ritchie, Christine",
      "Rix, Hans-Walter",
      "Robberto, Massimo",
      "Robinson, Gregory",
      "Robinson, Michael",
      "Robinson, Orion",
      "Rock, Frank",
      "Rodriguez, David",
      "Rodriguez Del Pino, Bruno",
      "Roellig, Thomas",
      "Rohrbach, Scott",
      "Roman, Anthony",
      "Romelfanger, Fred",
      "Rose, Perry",
      "Roteliuk, Anthony",
      "Roth, Marc",
      "Rothwell, Braden",
      "Rowlands, Neil",
      "Roy, Arpita",
      "Royer, Pierre",
      "Royle, Patricia",
      "Rui, Chunlei",
      "Rumler, Peter",
      "Runnels, Joel",
      "Russ, Melissa",
      "Rustamkulov, Zafar",
      "Ryden, Grant",
      "Ryer, Holly",
      "Sabata, Modhumita",
      "Sabatke, Derek",
      "Sabbi, Elena",
      "Samuelson, Bridget",
      "Sapp, Benjamin",
      "Sappington, Bradley",
      "Sargent, B.",
      "Sauer, Arne",
      "Scheithauer, Silvia",
      "Schlawin, Everett",
      "Schlitz, Joseph",
      "Schmitz, Tyler",
      "Schneider, Analyn",
      "Schreiber, J\u00fcrgen",
      "Schulze, Vonessa",
      "Schwab, Ryan",
      "Scott, John",
      "Sembach, Kenneth",
      "Shanahan, Clare",
      "Shaughnessy, Bryan",
      "Shaw, Richard",
      "Shawger, Nanci",
      "Shay, Christopher",
      "Sheehan, Evan",
      "Shen, Sharon",
      "Sherman, Allan",
      "Shiao, Bernard",
      "Shih, Hsin-Yi",
      "Shivaei, Irene",
      "Sienkiewicz, Matthew",
      "Sing, David",
      "Sirianni, Marco",
      "Sivaramakrishnan, Anand",
      "Skipper, Joy",
      "Sloan, G. C.",
      "Slocum, Christine",
      "Slowinski, Steven",
      "Smith, Erin",
      "Smith, Eric",
      "Smith, Denise",
      "Smith, Corbett",
      "Snyder, Gregory",
      "Soh, Warren",
      "Sohn, Sangmo Tony",
      "Soto, Christian",
      "Spencer, Richard",
      "Stallcup, Scott",
      "Stansberry, John",
      "Starr, Carl",
      "Starr, Elysia",
      "Stewart, Alphonso",
      "Stiavelli, Massimo",
      "Straughn, Amber",
      "Strickland, David",
      "Stys, Jeff",
      "Summers, Francis",
      "Sun, Fengwu",
      "Sunnquist, Ben",
      "Swade, Daryl",
      "Swam, Michael",
      "Swaters, Robert",
      "Swoish, Robby",
      "Taylor, Joanna M.",
      "Taylor, Rolanda",
      "Te Plate, Maurice",
      "Tea, Mason",
      "Teague, Kelly",
      "Telfer, Randal",
      "Temim, Tea",
      "Thatte, Deepashri",
      "Thompson, Christopher",
      "Thompson, Linda",
      "Thomson, Shaun",
      "Tikkanen, Tuomo",
      "Tippet, William",
      "Todd, Connor",
      "Toolan, Sharon",
      "Tran, Hien",
      "Trejo, Edwin",
      "Truong, Justin",
      "Tsukamoto, Chris",
      "Tustain, Samuel",
      "Tyra, Harrison",
      "Ubeda, Leonardo",
      "Underwood, Kelli",
      "Uzzo, Michael",
      "Van Campen, Julie",
      "Vandal, Thomas",
      "Vandenbussche, Bart",
      "Vila, Bego\u00f1a",
      "Volk, Kevin",
      "Wahlgren, Glenn",
      "Waldman, Mark",
      "Walker, Chanda",
      "Wander, Michel",
      "Warfield, Christine",
      "Warner, Gerald",
      "Wasiak, Matthew",
      "Watkins, Mitchell",
      "Weaver, Andrew",
      "Weilert, Mark",
      "Weiser, Nick",
      "Weiss, Ben",
      "Weissman, Sarah",
      "Welty, Alan",
      "West, Garrett",
      "Wheate, Lauren",
      "Wheatley, Elizabeth",
      "Wheeler, Thomas",
      "White, Rick",
      "Whiteaker, Kevin",
      "Whitehouse, Paul",
      "Whiteleather, Jennifer",
      "Whitman, William",
      "Williams, Christina",
      "Willmer, Christopher",
      "Willoughby, Scott",
      "Wilson, Andrew",
      "Wirth, Gregory",
      "Wislowski, Emily",
      "Wolf, Erin",
      "Wolfe, David",
      "Wolff, Schuyler",
      "Workman, Bill",
      "Wright, Ray",
      "Wu, Carl",
      "Wu, Rai",
      "Wymer, Kristen",
      "Yates, Kayla",
      "Yeager, Christopher",
      "Yeates, Jared",
      "Yerger, Ethan",
      "Yoon, Jinmi",
      "Young, Alice",
      "Yu, Susan",
      "Zak, Dean",
      "Zeidler, Peter",
      "Zhou, Julia",
      "Zielinski, Thomas",
      "Zincke, Cristian",
      "Zonak, Stephanie"
    ],
    "year": "2023",
    "pubdate": "2023-04-00",
    "doi": [
      "10.1088/1538-3873/acb293",
      "10.48550/arXiv.2207.05632"
    ],
    "title": "The Science Performance of JWST as Characterized in Commissioning",
    "pub": "Publications of the Astronomical Society of the Pacific",
    "volume": "135",
    "page": "048001",
    "citations": 501,
    "url": "https://ui.adsabs.harvard.edu/abs/2023PASP..135d8001R"
  },
  {
    "doctype": "article",
    "authors": [
      "Kiefer, F.",
      "H\u00e9brard, G.",
      "Martioli, E.",
      "Artigau, E.",
      "Doyon, R.",
      "Donati, J.-F.",
      "Cadieux, C.",
      "Carmona, A.",
      "Ciardi, D. R.",
      "Cristofari, P. I.",
      "de Almeida, L.",
      "Figueira, P.",
      "Gaidos, E.",
      "Gonzales, E.",
      "Lecavelier Des Etangs, A.",
      "Stassun, K. G.",
      "Arnold, L.",
      "Benneke, B.",
      "Boisse, I.",
      "Bonfils, X.",
      "Cook, N. J.",
      "Cort\u00e9s-Zuleta, P.",
      "Delfosse, X.",
      "do Nascimento, J. Dias",
      "Fausnaugh, M.",
      "Fong, W.",
      "Fouqu\u00e9, P.",
      "Forveille, T.",
      "Gomes da Silva, J.",
      "Hesse, K.",
      "K\u00f3sp\u00e1l, \u00c1.",
      "Lewis, H.",
      "Liu, C.-F.",
      "Martins, J. H. C.",
      "Paegert, M.",
      "Seager, S.",
      "Shang, H.",
      "Twicken, J. D.",
      "Vandal, T.",
      "Vinatier, S.",
      "Widemann, T.",
      "Winn, J. N."
    ],
    "year": "2023",
    "pubdate": "2023-02-00",
    "doi": [
      "10.1051/0004-6361/202245129",
      "10.48550/arXiv.2211.06205"
    ],
    "title": "A sub-Neptune planet around TOI-1695 discovered and characterized with SPIRou and TESS",
    "pub": "Astronomy and Astrophysics",
    "volume": "670",
    "page": "A136",
    "citations": 8,
    "url": "https://ui.adsabs.harvard.edu/abs/2023A&A...670A.136K"
  },
  {
    "doctype": "article",
    "authors": [
      "Sivaramakrishnan, Anand",
      "Tuthill, Peter",
      "Lloyd, James P.",
      "Greenbaum, Alexandra Z.",
      "Thatte, Deepashri",
      "Cooper, Rachel A.",
      "Vandal, Thomas",
      "Kammerer, Jens",
      "Sanchez-Bermudez, Joel",
      "Pope, Benjamin J. S.",
      "Blakely, Dori",
      "Albert, Lo\u00efc",
      "Cook, Neil J.",
      "Johnstone, Doug",
      "Martel, Andr\u00e9 R.",
      "Volk, Kevin",
      "Soulain, Anthony",
      "Artigau, \u00c9tienne",
      "Lafreni\u00e8re, David",
      "Willott, Chris J.",
      "Parmentier, S\u00e9bastien",
      "Ford, K. E. Saavik",
      "McKernan, Barry",
      "Vila, M. Bego\u00f1a",
      "Rowlands, Neil",
      "Doyon, Ren\u00e9",
      "Beaulieu, Mathilde",
      "Desdoigts, Louis",
      "Fullerton, Alexander W.",
      "De Furio, Matthew",
      "Goudfrooij, Paul",
      "Holfeltz, Sherie T.",
      "LaMassa, Stephanie",
      "Maszkiewicz, Michael",
      "Meyer, Michael R.",
      "Perrin, Marshall D.",
      "Pueyo, Laurent",
      "Sahlmann, Johannes",
      "Sohn, Sangmo Tony",
      "Teixeira, Paula S.",
      "Zheng, Sheng-hai"
    ],
    "year": "2023",
    "pubdate": "2023-01-00",
    "doi": [
      "10.1088/1538-3873/acaebd",
      "10.48550/arXiv.2210.17434"
    ],
    "title": "The Near Infrared Imager and Slitless Spectrograph for the James Webb Space Telescope. IV. Aperture Masking Interferometry",
    "pub": "Publications of the Astronomical Society of the Pacific",
    "volume": "135",
    "page": "015003",
    "citations": 28,
    "url": "https://ui.adsabs.harvard.edu/abs/2023PASP..135a5003S"
  },
  {
    "doctype": "article",
    "authors": [
      "Kammerer, Jens",
      "Cooper, Rachel A.",
      "Vandal, Thomas",
      "Thatte, Deepashri",
      "Martinache, Frantz",
      "Sivaramakrishnan, Anand",
      "Chaushev, Alexander",
      "Stolker, Tomas",
      "Lloyd, James P.",
      "Albert, Lo\u00efc",
      "Doyon, Ren\u00e9",
      "Sallum, Steph",
      "Perrin, Marshall D.",
      "Pueyo, Laurent",
      "M\u00e9rand, Antoine",
      "Gallenne, Alexandre",
      "Greenbaum, Alexandra",
      "Sanchez-Bermudez, Joel",
      "Blakely, Dori",
      "Johnstone, Doug",
      "Volk, Kevin",
      "Martel, Andre",
      "Goudfrooij, Paul",
      "Meyer, Michael R.",
      "Willott, Chris J.",
      "Furio, Matthew De",
      "Dang, Lisa",
      "Radica, Michael",
      "Noirot, Ga\u00ebl"
    ],
    "year": "2023",
    "pubdate": "2023-01-00",
    "doi": [
      "10.1088/1538-3873/ac9a74",
      "10.48550/arXiv.2210.17528"
    ],
    "title": "The Near Infrared Imager and Slitless Spectrograph for JWST. V. Kernel Phase Imaging and Data Analysis",
    "pub": "Publications of the Astronomical Society of the Pacific",
    "volume": "135",
    "page": "014502",
    "citations": 19,
    "url": "https://ui.adsabs.harvard.edu/abs/2023PASP..135a4502K"
  },
  {
    "doctype": "article",
    "authors": [
      "Cook, Neil James",
      "Artigau, \u00c9tienne",
      "Doyon, Ren\u00e9",
      "Hobson, Melissa",
      "Martioli, Eder",
      "Bouchy, Fran\u00e7ois",
      "Moutou, Claire",
      "Carmona, Andres",
      "Usher, Chris",
      "Fouqu\u00e9, Pascal",
      "Arnold, Luc",
      "Delfosse, Xavier",
      "Boisse, Isabelle",
      "Cadieux, Charles",
      "Vandal, Thomas",
      "Donati, Jean-Fran\u00e7ois",
      "Desli\u00e8res, Ariane"
    ],
    "year": "2022",
    "pubdate": "2022-11-00",
    "doi": [
      "10.1088/1538-3873/ac9e74",
      "10.48550/arXiv.2211.01358"
    ],
    "title": "APERO: A PipelinE to Reduce Observations-Demonstration with SPIRou",
    "pub": "Publications of the Astronomical Society of the Pacific",
    "volume": "134",
    "page": "114509",
    "citations": 76,
    "url": "https://ui.adsabs.harvard.edu/abs/2022PASP..134k4509C"
  },
  {
    "doctype": "article",
    "authors": [
      "Cadieux, Charles",
      "Doyon, Ren\u00e9",
      "Plotnykov, Mykhaylo",
      "H\u00e9brard, Guillaume",
      "Jahandar, Farbod",
      "Artigau, \u00c9tienne",
      "Valencia, Diana",
      "Cook, Neil J.",
      "Martioli, Eder",
      "Vandal, Thomas",
      "Donati, Jean-Fran\u00e7ois",
      "Cloutier, Ryan",
      "Narita, Norio",
      "Fukui, Akihiko",
      "Hirano, Teruyuki",
      "Bouchy, Fran\u00e7ois",
      "Cowan, Nicolas B.",
      "Gonzales, Erica J.",
      "Ciardi, David R.",
      "Stassun, Keivan G.",
      "Arnold, Luc",
      "Benneke, Bj\u00f6rn",
      "Boisse, Isabelle",
      "Bonfils, Xavier",
      "Carmona, Andr\u00e9s",
      "Cort\u00e9s-Zuleta, P\u00eda",
      "Delfosse, Xavier",
      "Forveille, Thierry",
      "Fouqu\u00e9, Pascal",
      "Gomes da Silva, Jo\u00e3o",
      "Jenkins, Jon M.",
      "Kiefer, Flavien",
      "K\u00f3sp\u00e1l, \u00c1gnes",
      "Lafreni\u00e8re, David",
      "Martins, Jorge H. C.",
      "Moutou, Claire",
      "do Nascimento, J.-D.",
      "Ould-Elhkim, Merwan",
      "Pelletier, Stefan",
      "Twicken, Joseph D.",
      "Bouma, Luke G.",
      "Cartwright, Scott",
      "Darveau-Bernier, Antoine",
      "Grankin, Konstantin",
      "Ikoma, Masahiro",
      "Kagetani, Taiki",
      "Kawauchi, Kiyoe",
      "Kodama, Takanori",
      "Kotani, Takayuki",
      "Latham, David W.",
      "Menou, Kristen",
      "Ricker, George",
      "Seager, Sara",
      "Tamura, Motohide",
      "Vanderspek, Roland",
      "Watanabe, Noriharu"
    ],
    "year": "2022",
    "pubdate": "2022-09-00",
    "doi": [
      "10.3847/1538-3881/ac7cea",
      "10.48550/arXiv.2208.06333"
    ],
    "title": "TOI-1452 b: SPIRou and TESS Reveal a Super-Earth in a Temperate Orbit Transiting an M4 Dwarf",
    "pub": "The Astronomical Journal",
    "volume": "164",
    "page": "96",
    "citations": 45,
    "url": "https://ui.adsabs.harvard.edu/abs/2022AJ....164...96C"
  },
  {
    "doctype": "article",
    "authors": [
      "Artigau, \u00c9tienne",
      "Cadieux, Charles",
      "Cook, Neil J.",
      "Doyon, Ren\u00e9",
      "Vandal, Thomas",
      "Donati, Jean-Fran\u00e7ois",
      "Moutou, Claire",
      "Delfosse, Xavier",
      "Fouqu\u00e9, Pascal",
      "Martioli, Eder",
      "Bouchy, Fran\u00e7ois",
      "Parsons, Jasmine",
      "Carmona, Andres",
      "Dumusque, Xavier",
      "Astudillo-Defru, Nicola",
      "Bonfils, Xavier",
      "Mignon, Lucille"
    ],
    "year": "2022",
    "pubdate": "2022-09-00",
    "doi": [
      "10.3847/1538-3881/ac7ce6",
      "10.48550/arXiv.2207.13524"
    ],
    "title": "Line-by-line Velocity Measurements: an Outlier-resistant Method for Precision Velocimetry",
    "pub": "The Astronomical Journal",
    "volume": "164",
    "page": "84",
    "citations": 90,
    "url": "https://ui.adsabs.harvard.edu/abs/2022AJ....164...84A"
  },
  {
    "doctype": "inproceedings",
    "authors": [
      "Kammerer, Jens",
      "Girard, Julien",
      "Carter, Aarynn L.",
      "Perrin, Marshall D.",
      "Cooper, Rachel",
      "Thatte, Deepashri",
      "Vandal, Thomas",
      "Leisenring, Jarron",
      "Wang, Jason",
      "Balmer, William O.",
      "Sivaramakrishnan, Anand",
      "Pueyo, Laurent",
      "Ward-Duong, Kimberly",
      "Sunnquist, Ben",
      "Adams Redai, J\u00e9a."
    ],
    "year": "2022",
    "pubdate": "2022-08-00",
    "doi": [
      "10.1117/12.2628865",
      "10.48550/arXiv.2208.00996"
    ],
    "title": "Performance of near-infrared high-contrast imaging methods with JWST from commissioning",
    "pub": "Space Telescopes and Instrumentation 2022: Optical, Infrared, and Millimeter Wave",
    "volume": "12180",
    "page": "121803N",
    "citations": 33,
    "url": "https://ui.adsabs.harvard.edu/abs/2022SPIE12180E..3NK"
  },
  {
    "doctype": "article",
    "authors": [
      "Martioli, E.",
      "H\u00e9brard, G.",
      "Fouqu\u00e9, P.",
      "Artigau, \u00c9.",
      "Donati, J.-F.",
      "Cadieux, C.",
      "Bellotti, S.",
      "Lecavelier des Etangs, A.",
      "Doyon, R.",
      "do Nascimento, J.-D.",
      "Arnold, L.",
      "Carmona, A.",
      "Cook, N. J.",
      "Cortes-Zuleta, P.",
      "de Almeida, L.",
      "Delfosse, X.",
      "Folsom, C. P.",
      "K\u00f6nig, P.-C.",
      "Moutou, C.",
      "Ould-Elhkim, M.",
      "Petit, P.",
      "Stassun, K. G.",
      "Vidotto, A. A.",
      "Vandal, T.",
      "Benneke, B.",
      "Boisse, I.",
      "Bonfils, X.",
      "Boyd, P.",
      "Brasseur, C.",
      "Charbonneau, D.",
      "Cloutier, R.",
      "Collins, K.",
      "Cristofari, P.",
      "Crossfield, I.",
      "D\u00edaz, R. F.",
      "Fausnaugh, M.",
      "Figueira, P.",
      "Forveille, T.",
      "Furlan, E.",
      "Girardin, E.",
      "Gnilka, C. L.",
      "Gomes da Silva, J.",
      "Gu, P.-G.",
      "Guerra, P.",
      "Howell, S. B.",
      "Hussain, G. A. J.",
      "Jenkins, J. M.",
      "Kiefer, F.",
      "Latham, D. W.",
      "Matson, R. A.",
      "Matthews, E. C.",
      "Morin, J.",
      "Naves, R.",
      "Ricker, G.",
      "Seager, S.",
      "Takami, M.",
      "Twicken, J. D.",
      "Vanderburg, A.",
      "Vanderspek, R.",
      "Winn, J."
    ],
    "year": "2022",
    "pubdate": "2022-04-00",
    "doi": [
      "10.1051/0004-6361/202142540",
      "10.48550/arXiv.2202.01259"
    ],
    "title": "TOI-1759 b: A transiting sub-Neptune around a low mass star characterized with SPIRou and TESS",
    "pub": "Astronomy and Astrophysics",
    "volume": "660",
    "page": "A86",
    "citations": 32,
    "url": "https://ui.adsabs.harvard.edu/abs/2022A&A...660A..86M"
  },
  {
    "doctype": "article",
    "authors": [
      "Artigau, \u00c9tienne",
      "H\u00e9brard, Guillaume",
      "Cadieux, Charles",
      "Vandal, Thomas",
      "Cook, Neil J.",
      "Doyon, Ren\u00e9",
      "Gagn\u00e9, Jonathan",
      "Moutou, Claire",
      "Martioli, Eder",
      "Frasca, Antonio",
      "Jahandar, Farbod",
      "Lafreni\u00e8re, David",
      "Malo, Lison",
      "Donati, Jean-Fran\u00e7ois",
      "Cort\u00e9s-Zuleta, P\u00eda",
      "Boisse, Isabelle",
      "Delfosse, Xavier",
      "Carmona, Andres",
      "Fouqu\u00e9, Pascal",
      "Morin, Julien",
      "Rowe, Jason",
      "Marino, Giuseppe",
      "Papini, Riccardo",
      "Ciardi, David R.",
      "Lund, Michael B.",
      "Martins, Jorge H. C.",
      "Pelletier, Stefan",
      "Arnold, Luc",
      "Bouchy, Fran\u00e7ois",
      "Forveille, Thierry",
      "Santos, Nuno C.",
      "Bonfils, Xavier",
      "Figueira, Pedro",
      "Fausnaugh, Michael",
      "Ricker, George",
      "Latham, David W.",
      "Seager, Sara",
      "Winn, Joshua N.",
      "Jenkins, Jon M.",
      "Ting, Eric B.",
      "Torres, Guillermo",
      "Gomes da Silva, Jo\u00e3o"
    ],
    "year": "2021",
    "pubdate": "2021-10-00",
    "doi": [
      "10.3847/1538-3881/ac096d",
      "10.48550/arXiv.2106.04536"
    ],
    "title": "TOI-1278 B: SPIRou Unveils a Rare Brown Dwarf Companion in Close-in Orbit around an M Dwarf",
    "pub": "The Astronomical Journal",
    "volume": "162",
    "page": "144",
    "citations": 35,
    "url": "https://ui.adsabs.harvard.edu/abs/2021AJ....162..144A"
  },
  {
    "doctype": "article",
    "authors": [
      "Pelletier, Stefan",
      "Benneke, Bj\u00f6rn",
      "Darveau-Bernier, Antoine",
      "Boucher, Anne",
      "Cook, Neil J.",
      "Piaulet, Caroline",
      "Coulombe, Louis-Philippe",
      "Artigau, \u00c9tienne",
      "Lafreni\u00e8re, David",
      "Delisle, Simon",
      "Allart, Romain",
      "Doyon, Ren\u00e9",
      "Donati, Jean-Fran\u00e7ois",
      "Fouqu\u00e9, Pascal",
      "Moutou, Claire",
      "Cadieux, Charles",
      "Delfosse, Xavier",
      "H\u00e9brard, Guillaume",
      "Martins, Jorge H. C.",
      "Martioli, Eder",
      "Vandal, Thomas"
    ],
    "year": "2021",
    "pubdate": "2021-08-00",
    "doi": [
      "10.3847/1538-3881/ac0428",
      "10.48550/arXiv.2105.10513"
    ],
    "title": "Where Is the Water? Jupiter-like C/H Ratio but Strong H<SUB>2</SUB>O Depletion Found on \u03c4 Bo\u00f6tis b Using SPIRou",
    "pub": "The Astronomical Journal",
    "volume": "162",
    "page": "73",
    "citations": 97,
    "url": "https://ui.adsabs.harvard.edu/abs/2021AJ....162...73P"
  },
  {
    "doctype": "article",
    "authors": [
      "Vandal, Thomas",
      "Rameau, Julien",
      "Doyon, Ren\u00e9"
    ],
    "year": "2020",
    "pubdate": "2020-11-00",
    "doi": [
      "10.3847/1538-3881/abba30",
      "10.48550/arXiv.2009.09276"
    ],
    "title": "Dynamical Mass Estimates of the \u03b2 Pictoris Planetary System through Gaussian Process Stellar Activity Modeling",
    "pub": "The Astronomical Journal",
    "volume": "160",
    "page": "243",
    "citations": 9,
    "url": "https://ui.adsabs.harvard.edu/abs/2020AJ....160..243V"
  }
]